Workbook

Sheet Resumen
A1: Cruce Top 100 eCommerce México × LSIX
A2: Fuente del universo: Similarweb Top Ecommerce & Shopping MX (jul-2026, top 5 público) + ranking ecommerceguide.com (jul-2026) + conocimiento de mercado. Orden dentro de categoría ≈ relevancia; no es ranking de revenue.
A4: Categoría | B4: Targets | C4: Ya en CRM | D4: Fit Alto | E4: Agencia identificada
A5: Marketplace | B5: =COUNTIF(Top100_MX!$D$2:$D$101,A5) | C5: =COUNTIFS(Top100_MX!$D$2:$D$101,A5,Top100_MX!$K$2:$K$101,"Sí") | D5: =COUNTIFS(Top100_MX!$D$2:$D$101,A5,Top100_MX!$G$2:$G$101,"Alto*") | E5: =COUNTIFS(Top100_MX!$D$2:$D$101,A5,Top100_MX!$H$2:$H$101,"<>[PENDIENTE]")-COUNTIFS(Top100_MX!$D$2:$D$101,A5,Top100_MX!$H$2:$H$101,"—")
A6: Departamental | B6: =COUNTIF(Top100_MX!$D$2:$D$101,A6) | C6: =COUNTIFS(Top100_MX!$D$2:$D$101,A6,Top100_MX!$K$2:$K$101,"Sí") | D6: =COUNTIFS(Top100_MX!$D$2:$D$101,A6,Top100_MX!$G$2:$G$101,"Alto*") | E6: =COUNTIFS(Top100_MX!$D$2:$D$101,A6,Top100_MX!$H$2:$H$101,"<>[PENDIENTE]")-COUNTIFS(Top100_MX!$D$2:$D$101,A6,Top100_MX!$H$2:$H$101,"—")
A7: Autoservicio / Grocery | B7: =COUNTIF(Top100_MX!$D$2:$D$101,A7) | C7: =COUNTIFS(Top100_MX!$D$2:$D$101,A7,Top100_MX!$K$2:$K$101,"Sí") | D7: =COUNTIFS(Top100_MX!$D$2:$D$101,A7,Top100_MX!$G$2:$G$101,"Alto*") | E7: =COUNTIFS(Top100_MX!$D$2:$D$101,A7,Top100_MX!$H$2:$H$101,"<>[PENDIENTE]")-COUNTIFS(Top100_MX!$D$2:$D$101,A7,Top100_MX!$H$2:$H$101,"—")
A8: Delivery / QSR | B8: =COUNTIF(Top100_MX!$D$2:$D$101,A8) | C8: =COUNTIFS(Top100_MX!$D$2:$D$101,A8,Top100_MX!$K$2:$K$101,"Sí") | D8: =COUNTIFS(Top100_MX!$D$2:$D$101,A8,Top100_MX!$G$2:$G$101,"Alto*") | E8: =COUNTIFS(Top100_MX!$D$2:$D$101,A8,Top100_MX!$H$2:$H$101,"<>[PENDIENTE]")-COUNTIFS(Top100_MX!$D$2:$D$101,A8,Top100_MX!$H$2:$H$101,"—")
A9: Farmacia | B9: =COUNTIF(Top100_MX!$D$2:$D$101,A9) | C9: =COUNTIFS(Top100_MX!$D$2:$D$101,A9,Top100_MX!$K$2:$K$101,"Sí") | D9: =COUNTIFS(Top100_MX!$D$2:$D$101,A9,Top100_MX!$G$2:$G$101,"Alto*") | E9: =COUNTIFS(Top100_MX!$D$2:$D$101,A9,Top100_MX!$H$2:$H$101,"<>[PENDIENTE]")-COUNTIFS(Top100_MX!$D$2:$D$101,A9,Top100_MX!$H$2:$H$101,"—")
A10: Beauty | B10: =COUNTIF(Top100_MX!$D$2:$D$101,A10) | C10: =COUNTIFS(Top100_MX!$D$2:$D$101,A10,Top100_MX!$K$2:$K$101,"Sí") | D10: =COUNTIFS(Top100_MX!$D$2:$D$101,A10,Top100_MX!$G$2:$G$101,"Alto*") | E10: =COUNTIFS(Top100_MX!$D$2:$D$101,A10,Top100_MX!$H$2:$H$101,"<>[PENDIENTE]")-COUNTIFS(Top100_MX!$D$2:$D$101,A10,Top100_MX!$H$2:$H$101,"—")
A11: Moda / Calzado | B11: =COUNTIF(Top100_MX!$D$2:$D$101,A11) | C11: =COUNTIFS(Top100_MX!$D$2:$D$101,A11,Top100_MX!$K$2:$K$101,"Sí") | D11: =COUNTIFS(Top100_MX!$D$2:$D$101,A11,Top100_MX!$G$2:$G$101,"Alto*") | E11: =COUNTIFS(Top100_MX!$D$2:$D$101,A11,Top100_MX!$H$2:$H$101,"<>[PENDIENTE]")-COUNTIFS(Top100_MX!$D$2:$D$101,A11,Top100_MX!$H$2:$H$101,"—")
A12: Deportes | B12: =COUNTIF(Top100_MX!$D$2:$D$101,A12) | C12: =COUNTIFS(Top100_MX!$D$2:$D$101,A12,Top100_MX!$K$2:$K$101,"Sí") | D12: =COUNTIFS(Top100_MX!$D$2:$D$101,A12,Top100_MX!$G$2:$G$101,"Alto*") | E12: =COUNTIFS(Top100_MX!$D$2:$D$101,A12,Top100_MX!$H$2:$H$101,"<>[PENDIENTE]")-COUNTIFS(Top100_MX!$D$2:$D$101,A12,Top100_MX!$H$2:$H$101,"—")
A13: Electrónica / Tech | B13: =COUNTIF(Top100_MX!$D$2:$D$101,A13) | C13: =COUNTIFS(Top100_MX!$D$2:$D$101,A13,Top100_MX!$K$2:$K$101,"Sí") | D13: =COUNTIFS(Top100_MX!$D$2:$D$101,A13,Top100_MX!$G$2:$G$101,"Alto*") | E13: =COUNTIFS(Top100_MX!$D$2:$D$101,A13,Top100_MX!$H$2:$H$101,"<>[PENDIENTE]")-COUNTIFS(Top100_MX!$D$2:$D$101,A13,Top100_MX!$H$2:$H$101,"—")
A14: Hogar / Oficina / Variedad | B14: =COUNTIF(Top100_MX!$D$2:$D$101,A14) | C14: =COUNTIFS(Top100_MX!$D$2:$D$101,A14,Top100_MX!$K$2:$K$101,"Sí") | D14: =COUNTIFS(Top100_MX!$D$2:$D$101,A14,Top100_MX!$G$2:$G$101,"Alto*") | E14: =COUNTIFS(Top100_MX!$D$2:$D$101,A14,Top100_MX!$H$2:$H$101,"<>[PENDIENTE]")-COUNTIFS(Top100_MX!$D$2:$D$101,A14,Top100_MX!$H$2:$H$101,"—")
A15: Travel / Movilidad | B15: =COUNTIF(Top100_MX!$D$2:$D$101,A15) | C15: =COUNTIFS(Top100_MX!$D$2:$D$101,A15,Top100_MX!$K$2:$K$101,"Sí") | D15: =COUNTIFS(Top100_MX!$D$2:$D$101,A15,Top100_MX!$G$2:$G$101,"Alto*") | E15: =COUNTIFS(Top100_MX!$D$2:$D$101,A15,Top100_MX!$H$2:$H$101,"<>[PENDIENTE]")-COUNTIFS(Top100_MX!$D$2:$D$101,A15,Top100_MX!$H$2:$H$101,"—")
A16: Entretenimiento / Ticketing | B16: =COUNTIF(Top100_MX!$D$2:$D$101,A16) | C16: =COUNTIFS(Top100_MX!$D$2:$D$101,A16,Top100_MX!$K$2:$K$101,"Sí") | D16: =COUNTIFS(Top100_MX!$D$2:$D$101,A16,Top100_MX!$G$2:$G$101,"Alto*") | E16: =COUNTIFS(Top100_MX!$D$2:$D$101,A16,Top100_MX!$H$2:$H$101,"<>[PENDIENTE]")-COUNTIFS(Top100_MX!$D$2:$D$101,A16,Top100_MX!$H$2:$H$101,"—")
... A20: Telco | B20: =COUNTIF(Top100_MX!$D$2:$D$101,A20) | C20: =COUNTIFS(Top100_MX!$D$2:$D$101,A20,Top100_MX!$K$2:$K$101,"Sí") | D20: =COUNTIFS(Top100_MX!$D$2:$D$101,A20,Top100_MX!$G$2:$G$101,"Alto*") | E20: =COUNTIFS(Top100_MX!$D$2:$D$101,A20,Top100_MX!$H$2:$H$101,"<>[PENDIENTE]")-COUNTIFS(Top100_MX!$D$2:$D$101,A20,Top100_MX!$H$2:$H$101,"—")
A21: TOTAL | B21: =SUM(B5:B20) | C21: =SUM(C5:C20) | D21: =SUM(D5:D20) | E21: =SUM(E5:E20)
A23: Leyenda: celdas amarillas en Top100_MX (Relación Andrés, Acción) son de llenado manual con dropdown. 'Agencia performance conocida' solo se llena con fuente pública o credencial LSIX; [PENDIENTE] = no hay info pública verificada.

Sheet Top100_MX
A1: # | B1: Empresa | C1: Dominio | D1: Categoría | E1: Subcategoría · Tipo | F1: App transaccional | G1: Fit CPA (hipótesis) | H1: Agencia performance conocida | I1: Estatus / fuente | J1: Decisor típico | K1: En CRM LSIX | L1: Relación Andrés | M1: Acción
A2: 1 | B2: Mercado Libre | C2: mercadolibre.com.mx | D2: Marketplace | E2: Marketplace · Marketplace | F2: Sí | G2: Bajo (growth in-house + afiliados propio) | H2: [PENDIENTE] | I2: Sin anuncio público de agencia de performance; compra de medios mayormente in-house | J2: Head of User Growth | K2: Sí | L2: Por confirmar
A3: 2 | B3: Amazon México | C3: amazon.com.mx | D3: Marketplace | E3: Marketplace · Marketplace | F3: Sí | G3: Bajo (procurement global) | H3: Omnicom Media Group (cuenta Américas, 2025) | I3: Asignación regional reportada por COMvergence vía MarketingDirecto; operación MX por validar | J3: Head of Marketing MX | K3: Sí | L3: Por confirmar
A4: 3 | B4: Temu | C4: temu.com | D4: Marketplace | E4: Marketplace · Cross-border | F4: Sí | G4: Bajo (UA in-house global, CPA agresivo propio) | H4: [PENDIENTE] | I4: Sin info pública MX | J4: Regional Growth Lead | K4: No | L4: Por confirmar
A5: 4 | B5: AliExpress | C5: aliexpress.com | D5: Marketplace | E5: Marketplace · Cross-border | F5: Sí | G5: Bajo | H5: [PENDIENTE] | I5: Sin info pública MX | J5: Regional Marketing LatAm | K5: No | L5: Por confirmar
A6: 5 | B6: Shein | C6: shein.com.mx | D6: Marketplace | E6: Marketplace · Cross-border / fast fashion | F6: Sí | G6: Medio (compran UA a CPA con partners) | H6: [PENDIENTE] | I6: Sin info pública MX | J6: Head of Performance LatAm | K6: No | L6: Por confirmar
A7: 6 | B7: Claro Shop (Grupo Carso) | C7: claroshop.com | D7: Marketplace | E7: Marketplace · Marketplace | F7: Sí | G7: Medio | H7: [PENDIENTE] | I7: Sin info pública | J7: Director Comercial Digital | K7: No | L7: Por confirmar
A8: 7 | B8: Liverpool | C8: liverpool.com.mx | D8: Departamental | E8: Departamental · Omnicanal | F8: Sí | G8: Alto | H8: [PENDIENTE] | I8: Sin anuncio público reciente de cuenta de performance | J8: Director Omnicanal / Medios | K8: Sí | L8: Por confirmar
A9: 8 | B9: Suburbia | C9: suburbia.com.mx | D9: Departamental | E9: Departamental · Omnicanal | F9: Sí | G9: Alto (misma decisión que Liverpool) | H9: [PENDIENTE] | I9: Mismo grupo que Liverpool | J9: Director Digital Suburbia | K9: No | L9: Por confirmar
A10: 9 | B10: El Palacio de Hierro | C10: elpalaciodehierro.com | D10: Departamental | E10: Departamental · Omnicanal premium | F10: Sí | G10: Alto (ticket alto, % revenue) | H10: [PENDIENTE] | I10: Sin info pública | J10: Director E-commerce | K10: No | L10: Por confirmar
A11: 10 | B11: Sears México (Grupo Carso) | C11: sears.com.mx | D11: Departamental | E11: Departamental · Omnicanal | F11: Sí | G11: Medio | H11: [PENDIENTE] | I11: Sin info pública | J11: Gerente E-commerce | K11: No | L11: Por confirmar
A12: 11 | B12: Sanborns | C12: sanborns.com.mx | D12: Departamental | E12: Departamental · Omnicanal | F12: Sí | G12: Medio | H12: [PENDIENTE] | I12: Sin info pública | J12: Gerente E-commerce | K12: No | L12: Por confirmar
A13: 12 | B13: Coppel | C13: coppel.com | D13: Departamental | E13: Departamental · Omnicanal + crédito | F13: Sí | G13: Alto | H13: ABC Digital (portafolio: Coppel Access) | I13: Declarado por la agencia en su portafolio (Marketing4ecommerce); alcance en Coppel.com por validar | J13: Director E-commerce / Digital | K13: Sí | L13: Por confirmar
... A101: 100 | B101: Spin by OXXO (Femsa) | C101: spinbyoxxo.com.mx | D101: Fintech / BNPL / Wallet | E101: Fintech / wallet · App | F101: Sí | G101: Por validar (evento de pago) | H101: iProspect (dentsu) — cuenta de medios OXXO, dic 2025 | I101: Anuncio de prensa (MarketingInsiderReview, 16-dic-2025); alcance sobre Spin por validar | J101: Head of Growth Spin | K101: Sí | L101: Por confirmar

Sheet Listas
A1: Relación | B1: Acción
A2: Super Brother | B2: Agregar al CRM
A3: Cliente | B3: Ya en CRM
A4: Conocido | B4: Descartar
A5: Al amigo de un amigo | B5: Nutrir (fase 2)
A6: Sin relación | B6: Validar fit
A7: Por confirmar

Sheet Metodo_Agencias
A1: Cómo completar 'Agencia performance conocida' (en orden de rendimiento)
A3: 1. LinkedIn Sales Navigator: buscar empleados de agencias (iProspect, Starcom, OMD, PHD, Wavemaker, Mindshare, Initiative, Havas, ABC Digital, Elogia, t2ó, Grupo W) con la marca en su headline o experiencia ('Account Director · Liverpool').
A4: 2. Google Ads Transparency Center (skill ads-transparency-probe): el advertiser verificado a veces es la agencia, no la marca. Confirma quién opera la cuenta.
A5: 3. Meta Ad Library: Page Transparency → 'Organizations that manage this Page' muestra agencias con acceso al Business Manager.
A6: 4. Merca2.0 Ranking de Agencias (julio, anual) y MediaBook: listado de clientes por agencia.
A7: 5. Press releases de asignación (Merca2.0, Adlatina, MarketingInsiderReview, El Publicista). Solo cuentas grandes se anuncian.
A8: 6. Pregunta directa en discovery: '¿Quién opera hoy su paid media y bajo qué modelo de fee?' — es dato de objeción (slide 8 del playbook), no solo de mapeo.
