Workbook

Sheet Resumen
A1: Pixeles y ad tech instalados — Top 100 eCommerce México × LSIX
A2: Vendors agregados por solicitud (21-ago): Ogury, Quantcast, Smarterclick, Acuity Ads/illumin, AppNexus, Google Dynamic Remarketing (Taboola y Xandr ya estaban). Método: (1) navegador headless Chromium capturando todas las requests de red de la home (equivalente a Ghostery), ~10s + scroll; (2) HTML + contenedores GTM. Solo home page: pixeles que disparan únicamente en checkout/thank-you pueden no aparecer. Fecha: 21-ago-2026.
A4: Sitios escaneados | B4: 100
A5: Con lectura válida | B5: =B4-B6 -> 76
A6: Bloqueados (pendiente Chrome/Ghostery) | B6: =COUNTIF(Matriz_Pixeles!F3:F102,"BLOQUEADO*") -> 24
A8: Vendor / pixel | B8: Categoría | C8: # sitios | D8: % de sitios con lectura
A9: Google Ads / gtag | B9: Paid media | C9: =SUM(Matriz_Pixeles!K3:K102) -> 57 | D9: =IF($B$5=0,0,C9/$B$5) -> 0.75
A10: Meta Pixel | B10: Paid media | C10: =SUM(Matriz_Pixeles!L3:L102) -> 48 | D10: =IF($B$5=0,0,C10/$B$5) -> 0.63157895
A11: TikTok Pixel | B11: Paid media | C11: =SUM(Matriz_Pixeles!M3:M102) -> 42 | D11: =IF($B$5=0,0,C11/$B$5) -> 0.55263158
A12: Pinterest Tag | B12: Paid media | C12: =SUM(Matriz_Pixeles!N3:N102) -> 13 | D12: =IF($B$5=0,0,C12/$B$5) -> 0.17105263
A13: Snap Pixel | B13: Paid media | C13: =SUM(Matriz_Pixeles!O3:O102) -> 1 | D13: =IF($B$5=0,0,C13/$B$5) -> 0.013157895
A14: LinkedIn Insight | B14: Paid media | C14: =SUM(Matriz_Pixeles!P3:P102) -> 6 | D14: =IF($B$5=0,0,C14/$B$5) -> 0.078947368
A15: X / Twitter Pixel | B15: Paid media | C15: =SUM(Matriz_Pixeles!Q3:Q102) -> 11 | D15: =IF($B$5=0,0,C15/$B$5) -> 0.14473684
A16: Microsoft Ads (UET) | B16: Paid media | C16: =SUM(Matriz_Pixeles!R3:R102) -> 25 | D16: =IF($B$5=0,0,C16/$B$5) -> 0.32894737
A17: Amazon Ads | B17: Paid media | C17: =SUM(Matriz_Pixeles!S3:S102) -> 7 | D17: =IF($B$5=0,0,C17/$B$5) -> 0.092105263
A18: Criteo | B18: Retargeting / CPA | C18: =SUM(Matriz_Pixeles!T3:T102) -> 11 | D18: =IF($B$5=0,0,C18/$B$5) -> 0.14473684
A19: RTB House | B19: Retargeting / CPA | C19: =SUM(Matriz_Pixeles!U3:U102) -> 20 | D19: =IF($B$5=0,0,C19/$B$5) -> 0.26315789
A20: Google Dynamic Remarketing | B20: Retargeting / CPA | C20: =SUM(Matriz_Pixeles!V3:V102) -> 23 | D20: =IF($B$5=0,0,C20/$B$5) -> 0.30263158
A21: Smarterclick | B21: Retargeting / CPA | C21: =SUM(Matriz_Pixeles!W3:W102) -> 1 | D21: =IF($B$5=0,0,C21/$B$5) -> 0.013157895
A22: Taboola | B22: Native | C22: =SUM(Matriz_Pixeles!X3:X102) -> 8 | D22: =IF($B$5=0,0,C22/$B$5) -> 0.10526316
A23: Outbrain | B23: Native | C23: =SUM(Matriz_Pixeles!Y3:Y102) -> 3 | D23: =IF($B$5=0,0,C23/$B$5) -> 0.039473684
A24: Awin | B24: Afiliados | C24: =SUM(Matriz_Pixeles!Z3:Z102) -> 16 | D24: =IF($B$5=0,0,C24/$B$5) -> 0.21052632
A25: Impact | B25: Afiliados | C25: =SUM(Matriz_Pixeles!AA3:AA102) -> 0 | D25: =IF($B$5=0,0,C25/$B$5) -> 0
A26: CJ Affiliate | B26: Afiliados | C26: =SUM(Matriz_Pixeles!AB3:AB102) -> 0 | D26: =IF($B$5=0,0,C26/$B$5) -> 0
A27: Rakuten Advertising | B27: Afiliados | C27: =SUM(Matriz_Pixeles!AC3:AC102) -> 1 | D27: =IF($B$5=0,0,C27/$B$5) -> 0.013157895
A28: Admitad | B28: Afiliados | C28: =SUM(Matriz_Pixeles!AD3:AD102) -> 10 | D28: =IF($B$5=0,0,C28/$B$5) -> 0.13157895
A29: Soicos | B29: Afiliados | C29: =SUM(Matriz_Pixeles!AE3:AE102) -> 8 | D29: =IF($B$5=0,0,C29/$B$5) -> 0.10526316
A30: Partnerize | B30: Afiliados | C30: =SUM(Matriz_Pixeles!AF3:AF102) -> 1 | D30: =IF($B$5=0,0,C30/$B$5) -> 0.013157895
A31: AppsFlyer | B31: MMP / App | C31: =SUM(Matriz_Pixeles!AG3:AG102) -> 9 | D31: =IF($B$5=0,0,C31/$B$5) -> 0.11842105
A32: Adjust | B32: MMP / App | C32: =SUM(Matriz_Pixeles!AH3:AH102) -> 2 | D32: =IF($B$5=0,0,C32/$B$5) -> 0.026315789
A33: Branch | B33: MMP / App | C33: =SUM(Matriz_Pixeles!AI3:AI102) -> 0 | D33: =IF($B$5=0,0,C33/$B$5) -> 0
A34: Kochava | B34: MMP / App | C34: =SUM(Matriz_Pixeles!AJ3:AJ102) -> 1 | D34: =IF($B$5=0,0,C34/$B$5) -> 0.013157895
A35: Singular | B35: MMP / App | C35: =SUM(Matriz_Pixeles!AK3:AK102) -> 6 | D35: =IF($B$5=0,0,C35/$B$5) -> 0.078947368
A36: DoubleClick Floodlight / DV360 / CM360 | B36: Programmatic (Google) | C36: =SUM(Matriz_Pixeles!AL3:AL102) -> 48 | D36: =IF($B$5=0,0,C36/$B$5) -> 0.63157895
A37: Adform | B37: Programmatic | C37: =SUM(Matriz_Pixeles!AM3:AM102) -> 3 | D37: =IF($B$5=0,0,C37/$B$5) -> 0.039473684
A38: Xandr / AppNexus | B38: Programmatic | C38: =SUM(Matriz_Pixeles!AN3:AN102) -> 5 | D38: =IF($B$5=0,0,C38/$B$5) -> 0.065789474
A39: The Trade Desk | B39: Programmatic | C39: =SUM(Matriz_Pixeles!AO3:AO102) -> 6 | D39: =IF($B$5=0,0,C39/$B$5) -> 0.078947368
A40: Ogury | B40: Programmatic | C40: =SUM(Matriz_Pixeles!AP3:AP102) -> 1 | D40: =IF($B$5=0,0,C40/$B$5) -> 0.013157895
A41: Acuity Ads / illumin | B41: Programmatic | C41: =SUM(Matriz_Pixeles!AQ3:AQ102) -> 1 | D41: =IF($B$5=0,0,C41/$B$5) -> 0.013157895
A42: AppNexus (Xandr legacy) | B42: Programmatic | C42: =SUM(Matriz_Pixeles!AR3:AR102) -> 5 | D42: =IF($B$5=0,0,C42/$B$5) -> 0.065789474
A43: MediaMath | B43: Programmatic | C43: =SUM(Matriz_Pixeles!AS3:AS102) -> 1 | D43: =IF($B$5=0,0,C43/$B$5) -> 0.013157895
A44: Yahoo DSP | B44: Programmatic | C44: =SUM(Matriz_Pixeles!AT3:AT102) -> 3 | D44: =IF($B$5=0,0,C44/$B$5) -> 0.039473684
A45: Seedtag | B45: Contextual | C45: =SUM(Matriz_Pixeles!AU3:AU102) -> 0 | D45: =IF($B$5=0,0,C45/$B$5) -> 0
A46: Teads | B46: Video/Native | C46: =SUM(Matriz_Pixeles!AV3:AV102) -> 1 | D46: =IF($B$5=0,0,C46/$B$5) -> 0.013157895
A47: Quantcast | B47: Data / DMP | C47: =SUM(Matriz_Pixeles!AW3:AW102) -> 1 | D47: =IF($B$5=0,0,C47/$B$5) -> 0.013157895
A48: Retargetly | B48: Data / DMP | C48: =SUM(Matriz_Pixeles!AX3:AX102) -> 2 | D48: =IF($B$5=0,0,C48/$B$5) -> 0.026315789
A49: Lotame | B49: Data / DMP | C49: =SUM(Matriz_Pixeles!AY3:AY102) -> 2 | D49: =IF($B$5=0,0,C49/$B$5) -> 0.026315789
A50: Oracle BlueKai | B50: Data / DMP | C50: =SUM(Matriz_Pixeles!AZ3:AZ102) -> 1 | D50: =IF($B$5=0,0,C50/$B$5) -> 0.013157895
A51: Adobe Audience Manager | B51: Data / DMP | C51: =SUM(Matriz_Pixeles!BA3:BA102) -> 10 | D51: =IF($B$5=0,0,C51/$B$5) -> 0.13157895
A52: LiveRamp | B52: Identity | C52: =SUM(Matriz_Pixeles!BB3:BB102) -> 5 | D52: =IF($B$5=0,0,C52/$B$5) -> 0.065789474
A53: ID5 | B53: Identity | C53: =SUM(Matriz_Pixeles!BC3:BC102) -> 1 | D53: =IF($B$5=0,0,C53/$B$5) -> 0.013157895
A54: Google Tag Manager | B54: Tag mgmt | C54: =SUM(Matriz_Pixeles!BD3:BD102) -> 54 | D54: =IF($B$5=0,0,C54/$B$5) -> 0.71052632
A55: Tealium | B55: Tag mgmt | C55: =SUM(Matriz_Pixeles!BE3:BE102) -> 6 | D55: =IF($B$5=0,0,C55/$B$5) -> 0.078947368
A56: GA4 | B56: Analytics | C56: =SUM(Matriz_Pixeles!BF3:BF102) -> 71 | D56: =IF($B$5=0,0,C56/$B$5) -> 0.93421053
A57: Adobe Analytics | B57: Analytics | C57: =SUM(Matriz_Pixeles!BG3:BG102) -> 14 | D57: =IF($B$5=0,0,C57/$B$5) -> 0.18421053
A58: Segment | B58: CDP | C58: =SUM(Matriz_Pixeles!BH3:BH102) -> 1 | D58: =IF($B$5=0,0,C58/$B$5) -> 0.013157895
A59: Hotjar | B59: UX | C59: =SUM(Matriz_Pixeles!BI3:BI102) -> 18 | D59: =IF($B$5=0,0,C59/$B$5) -> 0.23684211
A60: Microsoft Clarity | B60: UX | C60: =SUM(Matriz_Pixeles!BJ3:BJ102) -> 24 | D60: =IF($B$5=0,0,C60/$B$5) -> 0.31578947
A61: Contentsquare | B61: UX | C61: =SUM(Matriz_Pixeles!BK3:BK102) -> 20 | D61: =IF($B$5=0,0,C61/$B$5) -> 0.26315789
A62: FullStory | B62: UX | C62: =SUM(Matriz_Pixeles!BL3:BL102) -> 1 | D62: =IF($B$5=0,0,C62/$B$5) -> 0.013157895
A63: Insider | B63: Martech / CRM | C63: =SUM(Matriz_Pixeles!BM3:BM102) -> 2 | D63: =IF($B$5=0,0,C63/$B$5) -> 0.026315789
A64: Emarsys (SAP) | B64: Martech / CRM | C64: =SUM(Matriz_Pixeles!BN3:BN102) -> 12 | D64: =IF($B$5=0,0,C64/$B$5) -> 0.15789474
A65: Salesforce Marketing Cloud | B65: Martech / CRM | C65: =SUM(Matriz_Pixeles!BO3:BO102) -> 9 | D65: =IF($B$5=0,0,C65/$B$5) -> 0.11842105
A66: Braze | B66: Martech / CRM | C66: =SUM(Matriz_Pixeles!BP3:BP102) -> 2 | D66: =IF($B$5=0,0,C66/$B$5) -> 0.026315789
A67: CleverTap | B67: Martech / CRM | C67: =SUM(Matriz_Pixeles!BQ3:BQ102) -> 1 | D67: =IF($B$5=0,0,C67/$B$5) -> 0.013157895
A68: MoEngage | B68: Martech / CRM | C68: =SUM(Matriz_Pixeles!BR3:BR102) -> 2 | D68: =IF($B$5=0,0,C68/$B$5) -> 0.026315789
A69: Klaviyo | B69: Martech / CRM | C69: =SUM(Matriz_Pixeles!BS3:BS102) -> 4 | D69: =IF($B$5=0,0,C69/$B$5) -> 0.052631579
A70: HubSpot | B70: Martech / CRM | C70: =SUM(Matriz_Pixeles!BT3:BT102) -> 8 | D70: =IF($B$5=0,0,C70/$B$5) -> 0.10526316
A71: Connectif | B71: Martech / CRM | C71: =SUM(Matriz_Pixeles!BU3:BU102) -> 2 | D71: =IF($B$5=0,0,C71/$B$5) -> 0.026315789
A72: Bloomreach | B72: Martech / CRM | C72: =SUM(Matriz_Pixeles!BV3:BV102) -> 1 | D72: =IF($B$5=0,0,C72/$B$5) -> 0.013157895
A73: Dynamic Yield | B73: Personalización | C73: =SUM(Matriz_Pixeles!BW3:BW102) -> 1 | D73: =IF($B$5=0,0,C73/$B$5) -> 0.013157895
A74: Retail Rocket | B74: Personalización | C74: =SUM(Matriz_Pixeles!BX3:BX102) -> 0 | D74: =IF($B$5=0,0,C74/$B$5) -> 0
A75: Algolia | B75: Search | C75: =SUM(Matriz_Pixeles!BY3:BY102) -> 7 | D75: =IF($B$5=0,0,C75/$B$5) -> 0.092105263
A76: Bazaarvoice | B76: Reviews | C76: =SUM(Matriz_Pixeles!BZ3:BZ102) -> 9 | D76: =IF($B$5=0,0,C76/$B$5) -> 0.11842105
A77: Yotpo | B77: Reviews | C77: =SUM(Matriz_Pixeles!CA3:CA102) -> 3 | D77: =IF($B$5=0,0,C77/$B$5) -> 0.039473684
A78: Zendesk | B78: Chat | C78: =SUM(Matriz_Pixeles!CB3:CB102) -> 5 | D78: =IF($B$5=0,0,C78/$B$5) -> 0.065789474
A79: Intercom | B79: Chat | C79: =SUM(Matriz_Pixeles!CC3:CC102) -> 6 | D79: =IF($B$5=0,0,C79/$B$5) -> 0.078947368
A80: Shopify | B80: Plataforma | C80: =SUM(Matriz_Pixeles!CD3:CD102) -> 10 | D80: =IF($B$5=0,0,C80/$B$5) -> 0.13157895
A81: VTEX | B81: Plataforma | C81: =SUM(Matriz_Pixeles!CE3:CE102) -> 15 | D81: =IF($B$5=0,0,C81/$B$5) -> 0.19736842
A82: Salesforce Commerce Cloud | B82: Plataforma | C82: =SUM(Matriz_Pixeles!CF3:CF102) -> 3 | D82: =IF($B$5=0,0,C82/$B$5) -> 0.039473684
A83: Adobe Commerce (Magento) | B83: Plataforma | C83: =SUM(Matriz_Pixeles!CG3:CG102) -> 4 | D83: =IF($B$5=0,0,C83/$B$5) -> 0.052631579
A84: SAP Commerce | B84: Plataforma | C84: =SUM(Matriz_Pixeles!CH3:CH102) -> 4 | D84: =IF($B$5=0,0,C84/$B$5) -> 0.052631579
A85: Akamai | B85: Infra | C85: =SUM(Matriz_Pixeles!CI3:CI102) -> 0 | D85: =IF($B$5=0,0,C85/$B$5) -> 0
A86: Cloudflare | B86: Infra | C86: =SUM(Matriz_Pixeles!CJ3:CJ102) -> 19 | D86: =IF($B$5=0,0,C86/$B$5) -> 0.25
A88: Señales clave por categoría de empresa
A89: Categoría | B89: Sitios | C89: Con lectura | D89: RTB House | E89: Criteo | F89: Taboola/Outbrain | G89: Afiliados (cualquiera) | H89: MMP (cualquiera) | I89: TikTok | J89: Meta
A90: Marketplace | B90: =COUNTIF(Matriz_Pixeles!$D$3:$D$102,A90) -> 6 | C90: =COUNTIFS(Matriz_Pixeles!$D$3:$D$102,A90,Matriz_Pixeles!$F$3:$F$102,"<>BLOQUEADO*") -> 5 | D90: =SUMIF(Matriz_Pixeles!$D$3:$D$102,A90,Matriz_Pixeles!U$3:U$102) -> 1 | E90: =SUMIF(Matriz_Pixeles!$D$3:$D$102,A90,Matriz_Pixeles!T$3:T$102) -> 0 | F90: =SUMPRODUCT((Matriz_Pixeles!$D$3:$D$102=A90)*((Matriz_Pixeles!X$3:X$102=1)+(Matriz_Pixeles!Y$3:Y$102=1)>0)) -> 2 | G90: =SUMPRODUCT((Matriz_Pixeles!$D$3:$D$102=A90)*(((Matriz_Pixeles!Z$3:Z$102=1)+(Matriz_Pixeles!AA$3:AA$102=1)+(Matriz_Pixeles!AB$3:AB$102=1)+(Matriz_Pixeles!AC$3:AC$102=1)+(Matriz_Pixeles!AD$3:AD$102=1)+(Matriz_Pixeles!AE$3:AE$102=1)+(Matriz_Pixeles!AF$3:AF$102=1))>0)) -> 1 | H90: =SUMPRODUCT((Matriz_Pixeles!$D$3:$D$102=A90)*(((Matriz_Pixeles!AG$3:AG$102=1)+(Matriz_Pixeles!AH$3:AH$102=1)+(Matriz_Pixeles!AI$3:AI$102=1)+(Matriz_Pixeles!AJ$3:AJ$102=1)+(Matriz_Pixeles!AK$3:AK$102=1))>0)) -> 1 | I90: =SUMIF(Matriz_Pixeles!$D$3:$D$102,A90,Matriz_Pixeles!M$3:M$102) -> 1 | J90: =SUMIF(Matriz_Pixeles!$D$3:$D$102,A90,Matriz_Pixeles!L$3:L$102) -> 1
A91: Departamental | B91: =COUNTIF(Matriz_Pixeles!$D$3:$D$102,A91) -> 8 | C91: =COUNTIFS(Matriz_Pixeles!$D$3:$D$102,A91,Matriz_Pixeles!$F$3:$F$102,"<>BLOQUEADO*") -> 5 | D91: =SUMIF(Matriz_Pixeles!$D$3:$D$102,A91,Matriz_Pixeles!U$3:U$102) -> 3 | E91: =SUMIF(Matriz_Pixeles!$D$3:$D$102,A91,Matriz_Pixeles!T$3:T$102) -> 0 | F91: =SUMPRODUCT((Matriz_Pixeles!$D$3:$D$102=A91)*((Matriz_Pixeles!X$3:X$102=1)+(Matriz_Pixeles!Y$3:Y$102=1)>0)) -> 0 | G91: =SUMPRODUCT((Matriz_Pixeles!$D$3:$D$102=A91)*(((Matriz_Pixeles!Z$3:Z$102=1)+(Matriz_Pixeles!AA$3:AA$102=1)+(Matriz_Pixeles!AB$3:AB$102=1)+(Matriz_Pixeles!AC$3:AC$102=1)+(Matriz_Pixeles!AD$3:AD$102=1)+(Matriz_Pixeles!AE$3:AE$102=1)+(Matriz_Pixeles!AF$3:AF$102=1))>0)) -> 2 | H91: =SUMPRODUCT((Matriz_Pixeles!$D$3:$D$102=A91)*(((Matriz_Pixeles!AG$3:AG$102=1)+(Matriz_Pixeles!AH$3:AH$102=1)+(Matriz_Pixeles!AI$3:AI$102=1)+(Matriz_Pixeles!AJ$3:AJ$102=1)+(Matriz_Pixeles!AK$3:AK$102=1))>0)) -> 4 | I91: =SUMIF(Matriz_Pixeles!$D$3:$D$102,A91,Matriz_Pixeles!M$3:M$102) -> 4 | J91: =SUMIF(Matriz_Pixeles!$D$3:$D$102,A91,Matriz_Pixeles!L$3:L$102) -> 3
A92: Autoservicio / Grocery | B92: =COUNTIF(Matriz_Pixeles!$D$3:$D$102,A92) -> 9 | C92: =COUNTIFS(Matriz_Pixeles!$D$3:$D$102,A92,Matriz_Pixeles!$F$3:$F$102,"<>BLOQUEADO*") -> 6 | D92: =SUMIF(Matriz_Pixeles!$D$3:$D$102,A92,Matriz_Pixeles!U$3:U$102) -> 0 | E92: =SUMIF(Matriz_Pixeles!$D$3:$D$102,A92,Matriz_Pixeles!T$3:T$102) -> 0 | F92: =SUMPRODUCT((Matriz_Pixeles!$D$3:$D$102=A92)*((Matriz_Pixeles!X$3:X$102=1)+(Matriz_Pixeles!Y$3:Y$102=1)>0)) -> 0 | G92: =SUMPRODUCT((Matriz_Pixeles!$D$3:$D$102=A92)*(((Matriz_Pixeles!Z$3:Z$102=1)+(Matriz_Pixeles!AA$3:AA$102=1)+(Matriz_Pixeles!AB$3:AB$102=1)+(Matriz_Pixeles!AC$3:AC$102=1)+(Matriz_Pixeles!AD$3:AD$102=1)+(Matriz_Pixeles!AE$3:AE$102=1)+(Matriz_Pixeles!AF$3:AF$102=1))>0)) -> 0 | H92: =SUMPRODUCT((Matriz_Pixeles!$D$3:$D$102=A92)*(((Matriz_Pixeles!AG$3:AG$102=1)+(Matriz_Pixeles!AH$3:AH$102=1)+(Matriz_Pixeles!AI$3:AI$102=1)+(Matriz_Pixeles!AJ$3:AJ$102=1)+(Matriz_Pixeles!AK$3:AK$102=1))>0)) -> 1 | I92: =SUMIF(Matriz_Pixeles!$D$3:$D$102,A92,Matriz_Pixeles!M$3:M$102) -> 2 | J92: =SUMIF(Matriz_Pixeles!$D$3:$D$102,A92,Matriz_Pixeles!L$3:L$102) -> 1
A93: Delivery / QSR | B93: =COUNTIF(Matriz_Pixeles!$D$3:$D$102,A93) -> 7 | C93: =COUNTIFS(Matriz_Pixeles!$D$3:$D$102,A93,Matriz_Pixeles!$F$3:$F$102,"<>BLOQUEADO*") -> 7 | D93: =SUMIF(Matriz_Pixeles!$D$3:$D$102,A93,Matriz_Pixeles!U$3:U$102) -> 0 | E93: =SUMIF(Matriz_Pixeles!$D$3:$D$102,A93,Matriz_Pixeles!T$3:T$102) -> 2 | F93: =SUMPRODUCT((Matriz_Pixeles!$D$3:$D$102=A93)*((Matriz_Pixeles!X$3:X$102=1)+(Matriz_Pixeles!Y$3:Y$102=1)>0)) -> 2 | G93: =SUMPRODUCT((Matriz_Pixeles!$D$3:$D$102=A93)*(((Matriz_Pixeles!Z$3:Z$102=1)+(Matriz_Pixeles!AA$3:AA$102=1)+(Matriz_Pixeles!AB$3:AB$102=1)+(Matriz_Pixeles!AC$3:AC$102=1)+(Matriz_Pixeles!AD$3:AD$102=1)+(Matriz_Pixeles!AE$3:AE$102=1)+(Matriz_Pixeles!AF$3:AF$102=1))>0)) -> 1 | H93: =SUMPRODUCT((Matriz_Pixeles!$D$3:$D$102=A93)*(((Matriz_Pixeles!AG$3:AG$102=1)+(Matriz_Pixeles!AH$3:AH$102=1)+(Matriz_Pixeles!AI$3:AI$102=1)+(Matriz_Pixeles!AJ$3:AJ$102=1)+(Matriz_Pixeles!AK$3:AK$102=1))>0)) -> 3 | I93: =SUMIF(Matriz_Pixeles!$D$3:$D$102,A93,Matriz_Pixeles!M$3:M$102) -> 3 | J93: =SUMIF(Matriz_Pixeles!$D$3:$D$102,A93,Matriz_Pixeles!L$3:L$102) -> 5
A94: Farmacia | B94: =COUNTIF(Matriz_Pixeles!$D$3:$D$102,A94) -> 5 | C94: =COUNTIFS(Matriz_Pixeles!$D$3:$D$102,A94,Matriz_Pixeles!$F$3:$F$102,"<>BLOQUEADO*") -> 2 | D94: =SUMIF(Matriz_Pixeles!$D$3:$D$102,A94,Matriz_Pixeles!U$3:U$102) -> 1 | E94: =SUMIF(Matriz_Pixeles!$D$3:$D$102,A94,Matriz_Pixeles!T$3:T$102) -> 1 | F94: =SUMPRODUCT((Matriz_Pixeles!$D$3:$D$102=A94)*((Matriz_Pixeles!X$3:X$102=1)+(Matriz_Pixeles!Y$3:Y$102=1)>0)) -> 0 | G94: =SUMPRODUCT((Matriz_Pixeles!$D$3:$D$102=A94)*(((Matriz_Pixeles!Z$3:Z$102=1)+(Matriz_Pixeles!AA$3:AA$102=1)+(Matriz_Pixeles!AB$3:AB$102=1)+(Matriz_Pixeles!AC$3:AC$102=1)+(Matriz_Pixeles!AD$3:AD$102=1)+(Matriz_Pixeles!AE$3:AE$102=1)+(Matriz_Pixeles!AF$3:AF$102=1))>0)) -> 0 | H94: =SUMPRODUCT((Matriz_Pixeles!$D$3:$D$102=A94)*(((Matriz_Pixeles!AG$3:AG$102=1)+(Matriz_Pixeles!AH$3:AH$102=1)+(Matriz_Pixeles!AI$3:AI$102=1)+(Matriz_Pixeles!AJ$3:AJ$102=1)+(Matriz_Pixeles!AK$3:AK$102=1))>0)) -> 1 | I94: =SUMIF(Matriz_Pixeles!$D$3:$D$102,A94,Matriz_Pixeles!M$3:M$102) -> 2 | J94: =SUMIF(Matriz_Pixeles!$D$3:$D$102,A94,Matriz_Pixeles!L$3:L$102) -> 2
A95: Beauty | B95: =COUNTIF(Matriz_Pixeles!$D$3:$D$102,A95) -> 6 | C95: =COUNTIFS(Matriz_Pixeles!$D$3:$D$102,A95,Matriz_Pixeles!$F$3:$F$102,"<>BLOQUEADO*") -> 5 | D95: =SUMIF(Matriz_Pixeles!$D$3:$D$102,A95,Matriz_Pixeles!U$3:U$102) -> 1 | E95: =SUMIF(Matriz_Pixeles!$D$3:$D$102,A95,Matriz_Pixeles!T$3:T$102) -> 0 | F95: =SUMPRODUCT((Matriz_Pixeles!$D$3:$D$102=A95)*((Matriz_Pixeles!X$3:X$102=1)+(Matriz_Pixeles!Y$3:Y$102=1)>0)) -> 0 | G95: =SUMPRODUCT((Matriz_Pixeles!$D$3:$D$102=A95)*(((Matriz_Pixeles!Z$3:Z$102=1)+(Matriz_Pixeles!AA$3:AA$102=1)+(Matriz_Pixeles!AB$3:AB$102=1)+(Matriz_Pixeles!AC$3:AC$102=1)+(Matriz_Pixeles!AD$3:AD$102=1)+(Matriz_Pixeles!AE$3:AE$102=1)+(Matriz_Pixeles!AF$3:AF$102=1))>0)) -> 1 | H95: =SUMPRODUCT((Matriz_Pixeles!$D$3:$D$102=A95)*(((Matriz_Pixeles!AG$3:AG$102=1)+(Matriz_Pixeles!AH$3:AH$102=1)+(Matriz_Pixeles!AI$3:AI$102=1)+(Matriz_Pixeles!AJ$3:AJ$102=1)+(Matriz_Pixeles!AK$3:AK$102=1))>0)) -> 0 | I95: =SUMIF(Matriz_Pixeles!$D$3:$D$102,A95,Matriz_Pixeles!M$3:M$102) -> 1 | J95: =SUMIF(Matriz_Pixeles!$D$3:$D$102,A95,Matriz_Pixeles!L$3:L$102) -> 1
A96: Moda / Calzado | B96: =COUNTIF(Matriz_Pixeles!$D$3:$D$102,A96) -> 9 | C96: =COUNTIFS(Matriz_Pixeles!$D$3:$D$102,A96,Matriz_Pixeles!$F$3:$F$102,"<>BLOQUEADO*") -> 6 | D96: =SUMIF(Matriz_Pixeles!$D$3:$D$102,A96,Matriz_Pixeles!U$3:U$102) -> 1 | E96: =SUMIF(Matriz_Pixeles!$D$3:$D$102,A96,Matriz_Pixeles!T$3:T$102) -> 0 | F96: =SUMPRODUCT((Matriz_Pixeles!$D$3:$D$102=A96)*((Matriz_Pixeles!X$3:X$102=1)+(Matriz_Pixeles!Y$3:Y$102=1)>0)) -> 0 | G96: =SUMPRODUCT((Matriz_Pixeles!$D$3:$D$102=A96)*(((Matriz_Pixeles!Z$3:Z$102=1)+(Matriz_Pixeles!AA$3:AA$102=1)+(Matriz_Pixeles!AB$3:AB$102=1)+(Matriz_Pixeles!AC$3:AC$102=1)+(Matriz_Pixeles!AD$3:AD$102=1)+(Matriz_Pixeles!AE$3:AE$102=1)+(Matriz_Pixeles!AF$3:AF$102=1))>0)) -> 3 | H96: =SUMPRODUCT((Matriz_Pixeles!$D$3:$D$102=A96)*(((Matriz_Pixeles!AG$3:AG$102=1)+(Matriz_Pixeles!AH$3:AH$102=1)+(Matriz_Pixeles!AI$3:AI$102=1)+(Matriz_Pixeles!AJ$3:AJ$102=1)+(Matriz_Pixeles!AK$3:AK$102=1))>0)) -> 0 | I96: =SUMIF(Matriz_Pixeles!$D$3:$D$102,A96,Matriz_Pixeles!M$3:M$102) -> 4 | J96: =SUMIF(Matriz_Pixeles!$D$3:$D$102,A96,Matriz_Pixeles!L$3:L$102) -> 5
A97: Deportes | B97: =COUNTIF(Matriz_Pixeles!$D$3:$D$102,A97) -> 6 | C97: =COUNTIFS(Matriz_Pixeles!$D$3:$D$102,A97,Matriz_Pixeles!$F$3:$F$102,"<>BLOQUEADO*") -> 6 | D97: =SUMIF(Matriz_Pixeles!$D$3:$D$102,A97,Matriz_Pixeles!U$3:U$102) -> 3 | E97: =SUMIF(Matriz_Pixeles!$D$3:$D$102,A97,Matriz_Pixeles!T$3:T$102) -> 2 | F97: =SUMPRODUCT((Matriz_Pixeles!$D$3:$D$102=A97)*((Matriz_Pixeles!X$3:X$102=1)+(Matriz_Pixeles!Y$3:Y$102=1)>0)) -> 2 | G97: =SUMPRODUCT((Matriz_Pixeles!$D$3:$D$102=A97)*(((Matriz_Pixeles!Z$3:Z$102=1)+(Matriz_Pixeles!AA$3:AA$102=1)+(Matriz_Pixeles!AB$3:AB$102=1)+(Matriz_Pixeles!AC$3:AC$102=1)+(Matriz_Pixeles!AD$3:AD$102=1)+(Matriz_Pixeles!AE$3:AE$102=1)+(Matriz_Pixeles!AF$3:AF$102=1))>0)) -> 1 | H97: =SUMPRODUCT((Matriz_Pixeles!$D$3:$D$102=A97)*(((Matriz_Pixeles!AG$3:AG$102=1)+(Matriz_Pixeles!AH$3:AH$102=1)+(Matriz_Pixeles!AI$3:AI$102=1)+(Matriz_Pixeles!AJ$3:AJ$102=1)+(Matriz_Pixeles!AK$3:AK$102=1))>0)) -> 2 | I97: =SUMIF(Matriz_Pixeles!$D$3:$D$102,A97,Matriz_Pixeles!M$3:M$102) -> 3 | J97: =SUMIF(Matriz_Pixeles!$D$3:$D$102,A97,Matriz_Pixeles!L$3:L$102) -> 4
A98: Electrónica / Tech | B98: =COUNTIF(Matriz_Pixeles!$D$3:$D$102,A98) -> 7 | C98: =COUNTIFS(Matriz_Pixeles!$D$3:$D$102,A98,Matriz_Pixeles!$F$3:$F$102,"<>BLOQUEADO*") -> 6 | D98: =SUMIF(Matriz_Pixeles!$D$3:$D$102,A98,Matriz_Pixeles!U$3:U$102) -> 1 | E98: =SUMIF(Matriz_Pixeles!$D$3:$D$102,A98,Matriz_Pixeles!T$3:T$102) -> 1 | F98: =SUMPRODUCT((Matriz_Pixeles!$D$3:$D$102=A98)*((Matriz_Pixeles!X$3:X$102=1)+(Matriz_Pixeles!Y$3:Y$102=1)>0)) -> 1 | G98: =SUMPRODUCT((Matriz_Pixeles!$D$3:$D$102=A98)*(((Matriz_Pixeles!Z$3:Z$102=1)+(Matriz_Pixeles!AA$3:AA$102=1)+(Matriz_Pixeles!AB$3:AB$102=1)+(Matriz_Pixeles!AC$3:AC$102=1)+(Matriz_Pixeles!AD$3:AD$102=1)+(Matriz_Pixeles!AE$3:AE$102=1)+(Matriz_Pixeles!AF$3:AF$102=1))>0)) -> 4 | H98: =SUMPRODUCT((Matriz_Pixeles!$D$3:$D$102=A98)*(((Matriz_Pixeles!AG$3:AG$102=1)+(Matriz_Pixeles!AH$3:AH$102=1)+(Matriz_Pixeles!AI$3:AI$102=1)+(Matriz_Pixeles!AJ$3:AJ$102=1)+(Matriz_Pixeles!AK$3:AK$102=1))>0)) -> 0 | I98: =SUMIF(Matriz_Pixeles!$D$3:$D$102,A98,Matriz_Pixeles!M$3:M$102) -> 3 | J98: =SUMIF(Matriz_Pixeles!$D$3:$D$102,A98,Matriz_Pixeles!L$3:L$102) -> 3
A99: Hogar / Oficina / Variedad | B99: =COUNTIF(Matriz_Pixeles!$D$3:$D$102,A99) -> 7 | C99: =COUNTIFS(Matriz_Pixeles!$D$3:$D$102,A99,Matriz_Pixeles!$F$3:$F$102,"<>BLOQUEADO*") -> 5 | D99: =SUMIF(Matriz_Pixeles!$D$3:$D$102,A99,Matriz_Pixeles!U$3:U$102) -> 3 | E99: =SUMIF(Matriz_Pixeles!$D$3:$D$102,A99,Matriz_Pixeles!T$3:T$102) -> 2 | F99: =SUMPRODUCT((Matriz_Pixeles!$D$3:$D$102=A99)*((Matriz_Pixeles!X$3:X$102=1)+(Matriz_Pixeles!Y$3:Y$102=1)>0)) -> 1 | G99: =SUMPRODUCT((Matriz_Pixeles!$D$3:$D$102=A99)*(((Matriz_Pixeles!Z$3:Z$102=1)+(Matriz_Pixeles!AA$3:AA$102=1)+(Matriz_Pixeles!AB$3:AB$102=1)+(Matriz_Pixeles!AC$3:AC$102=1)+(Matriz_Pixeles!AD$3:AD$102=1)+(Matriz_Pixeles!AE$3:AE$102=1)+(Matriz_Pixeles!AF$3:AF$102=1))>0)) -> 3 | H99: =SUMPRODUCT((Matriz_Pixeles!$D$3:$D$102=A99)*(((Matriz_Pixeles!AG$3:AG$102=1)+(Matriz_Pixeles!AH$3:AH$102=1)+(Matriz_Pixeles!AI$3:AI$102=1)+(Matriz_Pixeles!AJ$3:AJ$102=1)+(Matriz_Pixeles!AK$3:AK$102=1))>0)) -> 1 | I99: =SUMIF(Matriz_Pixeles!$D$3:$D$102,A99,Matriz_Pixeles!M$3:M$102) -> 4 | J99: =SUMIF(Matriz_Pixeles!$D$3:$D$102,A99,Matriz_Pixeles!L$3:L$102) -> 3
A100: Travel / Movilidad | B100: =COUNTIF(Matriz_Pixeles!$D$3:$D$102,A100) -> 9 | C100: =COUNTIFS(Matriz_Pixeles!$D$3:$D$102,A100,Matriz_Pixeles!$F$3:$F$102,"<>BLOQUEADO*") -> 5 | D100: =SUMIF(Matriz_Pixeles!$D$3:$D$102,A100,Matriz_Pixeles!U$3:U$102) -> 2 | E100: =SUMIF(Matriz_Pixeles!$D$3:$D$102,A100,Matriz_Pixeles!T$3:T$102) -> 1 | F100: =SUMPRODUCT((Matriz_Pixeles!$D$3:$D$102=A100)*((Matriz_Pixeles!X$3:X$102=1)+(Matriz_Pixeles!Y$3:Y$102=1)>0)) -> 1 | G100: =SUMPRODUCT((Matriz_Pixeles!$D$3:$D$102=A100)*(((Matriz_Pixeles!Z$3:Z$102=1)+(Matriz_Pixeles!AA$3:AA$102=1)+(Matriz_Pixeles!AB$3:AB$102=1)+(Matriz_Pixeles!AC$3:AC$102=1)+(Matriz_Pixeles!AD$3:AD$102=1)+(Matriz_Pixeles!AE$3:AE$102=1)+(Matriz_Pixeles!AF$3:AF$102=1))>0)) -> 3 | H100: =SUMPRODUCT((Matriz_Pixeles!$D$3:$D$102=A100)*(((Matriz_Pixeles!AG$3:AG$102=1)+(Matriz_Pixeles!AH$3:AH$102=1)+(Matriz_Pixeles!AI$3:AI$102=1)+(Matriz_Pixeles!AJ$3:AJ$102=1)+(Matriz_Pixeles!AK$3:AK$102=1))>0)) -> 0 | I100: =SUMIF(Matriz_Pixeles!$D$3:$D$102,A100,Matriz_Pixeles!M$3:M$102) -> 2 | J100: =SUMIF(Matriz_Pixeles!$D$3:$D$102,A100,Matriz_Pixeles!L$3:L$102) -> 4
A101: Entretenimiento / Ticketing | B101: =COUNTIF(Matriz_Pixeles!$D$3:$D$102,A101) -> 4 | C101: =COUNTIFS(Matriz_Pixeles!$D$3:$D$102,A101,Matriz_Pixeles!$F$3:$F$102,"<>BLOQUEADO*") -> 2 | D101: =SUMIF(Matriz_Pixeles!$D$3:$D$102,A101,Matriz_Pixeles!U$3:U$102) -> 0 | E101: =SUMIF(Matriz_Pixeles!$D$3:$D$102,A101,Matriz_Pixeles!T$3:T$102) -> 0 | F101: =SUMPRODUCT((Matriz_Pixeles!$D$3:$D$102=A101)*((Matriz_Pixeles!X$3:X$102=1)+(Matriz_Pixeles!Y$3:Y$102=1)>0)) -> 0 | G101: =SUMPRODUCT((Matriz_Pixeles!$D$3:$D$102=A101)*(((Matriz_Pixeles!Z$3:Z$102=1)+(Matriz_Pixeles!AA$3:AA$102=1)+(Matriz_Pixeles!AB$3:AB$102=1)+(Matriz_Pixeles!AC$3:AC$102=1)+(Matriz_Pixeles!AD$3:AD$102=1)+(Matriz_Pixeles!AE$3:AE$102=1)+(Matriz_Pixeles!AF$3:AF$102=1))>0)) -> 1 | H101: =SUMPRODUCT((Matriz_Pixeles!$D$3:$D$102=A101)*(((Matriz_Pixeles!AG$3:AG$102=1)+(Matriz_Pixeles!AH$3:AH$102=1)+(Matriz_Pixeles!AI$3:AI$102=1)+(Matriz_Pixeles!AJ$3:AJ$102=1)+(Matriz_Pixeles!AK$3:AK$102=1))>0)) -> 0 | I101: =SUMIF(Matriz_Pixeles!$D$3:$D$102,A101,Matriz_Pixeles!M$3:M$102) -> 1 | J101: =SUMIF(Matriz_Pixeles!$D$3:$D$102,A101,Matriz_Pixeles!L$3:L$102) -> 1
... A105: Telco | B105: =COUNTIF(Matriz_Pixeles!$D$3:$D$102,A105) -> 2 | C105: =COUNTIFS(Matriz_Pixeles!$D$3:$D$102,A105,Matriz_Pixeles!$F$3:$F$102,"<>BLOQUEADO*") -> 2 | D105: =SUMIF(Matriz_Pixeles!$D$3:$D$102,A105,Matriz_Pixeles!U$3:U$102) -> 1 | E105: =SUMIF(Matriz_Pixeles!$D$3:$D$102,A105,Matriz_Pixeles!T$3:T$102) -> 0 | F105: =SUMPRODUCT((Matriz_Pixeles!$D$3:$D$102=A105)*((Matriz_Pixeles!X$3:X$102=1)+(Matriz_Pixeles!Y$3:Y$102=1)>0)) -> 0 | G105: =SUMPRODUCT((Matriz_Pixeles!$D$3:$D$102=A105)*(((Matriz_Pixeles!Z$3:Z$102=1)+(Matriz_Pixeles!AA$3:AA$102=1)+(Matriz_Pixeles!AB$3:AB$102=1)+(Matriz_Pixeles!AC$3:AC$102=1)+(Matriz_Pixeles!AD$3:AD$102=1)+(Matriz_Pixeles!AE$3:AE$102=1)+(Matriz_Pixeles!AF$3:AF$102=1))>0)) -> 0 | H105: =SUMPRODUCT((Matriz_Pixeles!$D$3:$D$102=A105)*(((Matriz_Pixeles!AG$3:AG$102=1)+(Matriz_Pixeles!AH$3:AH$102=1)+(Matriz_Pixeles!AI$3:AI$102=1)+(Matriz_Pixeles!AJ$3:AJ$102=1)+(Matriz_Pixeles!AK$3:AK$102=1))>0)) -> 0 | I105: =SUMIF(Matriz_Pixeles!$D$3:$D$102,A105,Matriz_Pixeles!M$3:M$102) -> 2 | J105: =SUMIF(Matriz_Pixeles!$D$3:$D$102,A105,Matriz_Pixeles!L$3:L$102) -> 2

Sheet Matriz_Pixeles
K1: Paid media | L1: Paid media | M1: Paid media | N1: Paid media | O1: Paid media | P1: Paid media | Q1: Paid media | R1: Paid media | S1: Paid media | T1: Retargeting / CPA | U1: Retargeting / CPA | V1: Retargeting / CPA | W1: Retargeting / CPA | X1: Native | Y1: Native | Z1: Afiliados | AA1: Afiliados | AB1: Afiliados | AC1: Afiliados | AD1: Afiliados | AE1: Afiliados | AF1: Afiliados | AG1: MMP / App | AH1: MMP / App | AI1: MMP / App | AJ1: MMP / App | AK1: MMP / App | AL1: Programmatic (Google) | AM1: Programmatic | AN1: Programmatic | AO1: Programmatic | AP1: Programmatic | AQ1: Programmatic | AR1: Programmatic | AS1: Programmatic | AT1: Programmatic | AU1: Contextual | AV1: Video/Native | AW1: Data / DMP | AX1: Data / DMP | AY1: Data / DMP | AZ1: Data / DMP | BA1: Data / DMP | BB1: Identity | BC1: Identity | BD1: Tag mgmt | BE1: Tag mgmt | BF1: Analytics | BG1: Analytics | BH1: CDP | BI1: UX | BJ1: UX | BK1: UX | BL1: UX | BM1: Martech / CRM | BN1: Martech / CRM | BO1: Martech / CRM | BP1: Martech / CRM | BQ1: Martech / CRM | BR1: Martech / CRM | BS1: Martech / CRM | BT1: Martech / CRM | BU1: Martech / CRM | BV1: Martech / CRM | BW1: Personalización | BX1: Personalización | BY1: Search | BZ1: Reviews | CA1: Reviews | CB1: Chat | CC1: Chat | CD1: Plataforma | CE1: Plataforma | CF1: Plataforma | CG1: Plataforma | CH1: Plataforma | CI1: Infra | CJ1: Infra
A2: # | B2: Empresa | C2: Dominio | D2: Categoría | E2: En CRM | F2: Estatus scan | G2: Método | H2: # trackers | I2: GTM IDs | J2: Señal CPA / fit LSIX | K2: Google Ads / gtag | L2: Meta Pixel | M2: TikTok Pixel | N2: Pinterest Tag | O2: Snap Pixel | P2: LinkedIn Insight | Q2: X / Twitter Pixel | R2: Microsoft Ads (UET) | S2: Amazon Ads | T2: Criteo | U2: RTB House | V2: Google Dynamic Remarketing | W2: Smarterclick | X2: Taboola | Y2: Outbrain | Z2: Awin | AA2: Impact | AB2: CJ Affiliate | AC2: Rakuten Advertising | AD2: Admitad | AE2: Soicos | AF2: Partnerize | AG2: AppsFlyer | AH2: Adjust | AI2: Branch | AJ2: Kochava | AK2: Singular | AL2: DoubleClick Floodlight / DV360 / CM360 | AM2: Adform | AN2: Xandr / AppNexus | AO2: The Trade Desk | AP2: Ogury | AQ2: Acuity Ads / illumin | AR2: AppNexus (Xandr legacy) | AS2: MediaMath | AT2: Yahoo DSP | AU2: Seedtag | AV2: Teads | AW2: Quantcast | AX2: Retargetly | AY2: Lotame | AZ2: Oracle BlueKai | BA2: Adobe Audience Manager | BB2: LiveRamp | BC2: ID5 | BD2: Google Tag Manager | BE2: Tealium | BF2: GA4 | BG2: Adobe Analytics | BH2: Segment | BI2: Hotjar | BJ2: Microsoft Clarity | BK2: Contentsquare | BL2: FullStory | BM2: Insider | BN2: Emarsys (SAP) | BO2: Salesforce Marketing Cloud | BP2: Braze | BQ2: CleverTap | BR2: MoEngage | BS2: Klaviyo | BT2: HubSpot | BU2: Connectif | BV2: Bloomreach | BW2: Dynamic Yield | BX2: Retail Rocket | BY2: Algolia | BZ2: Bazaarvoice | CA2: Yotpo | CB2: Zendesk | CC2: Intercom | CD2: Shopify | CE2: VTEX | CF2: Salesforce Commerce Cloud | CG2: Adobe Commerce (Magento) | CH2: SAP Commerce | CI2: Akamai | CJ2: Cloudflare
A3: 1 | B3: Mercado Libre | C3: mercadolibre.com.mx | D3: Marketplace | E3: Sí | F3: HTTP 200 | G3: Red (navegador) + HTML/GTM | H3: 3 | BF3: 1 | BI3: 1 | BK3: 1
A4: 2 | B4: Amazon México | C4: amazon.com.mx | D4: Marketplace | E4: Sí | F4: HTTP 202 | G4: HTML/GTM | H4: 1 | BK4: 1
A5: 3 | B5: Temu | C5: temu.com | D5: Marketplace | E5: No | F5: HTTP 200 | G5: HTML/GTM | H5: 3 | J5: Native/performance | K5: 1 | X5: 1 | BF5: 1
A6: 4 | B6: AliExpress | C6: aliexpress.com | D6: Marketplace | E6: No | F6: BLOQUEADO · revisar en Chrome/Ghostery | H6: 0
A7: 5 | B7: Shein | C7: shein.com.mx | D7: Marketplace | E7: No | F7: HTTP 200 | G7: HTML/GTM | H7: 7 | J7: Programa de afiliados activo (ya paga CPA) | K7: 1 | Z7: 1 | AD7: 1 | BF7: 1 | BN7: 1 | BT7: 1 | CB7: 1
A8: 6 | B8: Claro Shop (Grupo Carso) | C8: claroshop.com | D8: Marketplace | E8: No | F8: HTTP 200 | G8: Red (navegador) + HTML/GTM | H8: 16 | I8: GTM-K7PM8MQ | J8: Retargeting a CPA/CPC (RTB House/Criteo/Smarterclick) · MMP instalado (atribución app lista) · Native/performance | K8: 1 | L8: 1 | M8: 1 | U8: 1 | X8: 1 | AK8: 1 | AL8: 1 | AN8: 1 | AR8: 1 | AZ8: 1 | BD8: 1 | BF8: 1 | BI8: 1 | BN8: 1 | BY8: 1 | CA8: 1
A9: 7 | B9: Liverpool | C9: liverpool.com.mx | D9: Departamental | E9: Sí | F9: HTTP 403 · bloqueo bot (revisar en Chrome/Ghostery) | G9: HTML/GTM | H9: 10 | I9: GTM-KM2VZFW | J9: Retargeting a CPA/CPC (RTB House/Criteo/Smarterclick) · MMP instalado (atribución app lista) | K9: 1 | M9: 1 | R9: 1 | U9: 1 | AG9: 1 | AL9: 1 | BD9: 1 | BF9: 1 | BO9: 1 | BZ9: 1
A10: 8 | B10: Suburbia | C10: suburbia.com.mx | D10: Departamental | E10: No | F10: HTTP 200 | G10: Red (navegador) + HTML/GTM | H10: 12 | I10: GTM-KM2VZFW, GTM-P99XGLW | J10: Retargeting a CPA/CPC (RTB House/Criteo/Smarterclick) · MMP instalado (atribución app lista) | K10: 1 | L10: 1 | M10: 1 | N10: 1 | R10: 1 | U10: 1 | AG10: 1 | AL10: 1 | BD10: 1 | BF10: 1 | BO10: 1 | BZ10: 1
A11: 9 | B11: El Palacio de Hierro | C11: elpalaciodehierro.com | D11: Departamental | E11: No | F11: HTTP 200 | G11: Red (navegador) + HTML/GTM | H11: 18 | I11: GTM-S9GP | J11: Retargeting a CPA/CPC (RTB House/Criteo/Smarterclick) · Dynamic remarketing Google activo · Programa de afiliados activo (ya paga CPA) · MMP instalado (atribución app lista) | K11: 1 | L11: 1 | M11: 1 | N11: 1 | U11: 1 | V11: 1 | AE11: 1 | AG11: 1 | AL11: 1 | BD11: 1 | BF11: 1 | BK11: 1 | BM11: 1 | BO11: 1 | BT11: 1 | BZ11: 1 | CF11: 1 | CJ11: 1
A12: 10 | B12: Sears México (Grupo Carso) | C12: sears.com.mx | D12: Departamental | E12: No | F12: BLOQUEADO · revisar en Chrome/Ghostery | H12: 0
A13: 11 | B13: Sanborns | C13: sanborns.com.mx | D13: Departamental | E13: No | F13: BLOQUEADO · revisar en Chrome/Ghostery | H13: 0
A14: 12 | B14: Coppel | C14: coppel.com | D14: Departamental | E14: Sí | F14: HTTP 200 | G14: Red (navegador) | H14: 3 | I14: GTM-MLFDXSFC, GTM-MQC5RG5C, GTM-NL3WNDZV, GTM-NVKCT9W5, GTM-NXQMNBJG, GTM-P3VZMZXT, GTM-T58P8MMW, GTM-TD6ZZHT4, GTM-WTBN8XVR | BD14: 1 | BF14: 1 | BN14: 1
A15: 13 | B15: Elektra | C15: elektra.mx | D15: Departamental | E15: Sí | F15: HTTP 200 | G15: Red (navegador) + HTML/GTM | H15: 21 | I15: GTM-P7K53B9 | J15: Dynamic remarketing Google activo · Programa de afiliados activo (ya paga CPA) · MMP instalado (atribución app lista) | K15: 1 | L15: 1 | M15: 1 | N15: 1 | R15: 1 | V15: 1 | Z15: 1 | AE15: 1 | AG15: 1 | AL15: 1 | AN15: 1 | AR15: 1 | BA15: 1 | BD15: 1 | BE15: 1 | BF15: 1 | BG15: 1 | BN15: 1 | CC15: 1 | CE15: 1 | CJ15: 1
A16: 14 | B16: Walmart de México | C16: walmart.com.mx | D16: Autoservicio / Grocery | E16: Sí | F16: BLOQUEADO · revisar en Chrome/Ghostery | H16: 0
A17: 15 | B17: Bodega Aurrera | C17: bodegaaurrera.com.mx | D17: Autoservicio / Grocery | E17: Sí | F17: HTTP 200 · bloqueo bot (revisar en Chrome/Ghostery) | G17: Red (navegador) + HTML/GTM | H17: 3 | BA17: 1 | BF17: 1 | BG17: 1
A18: 16 | B18: Sam's Club México | C18: sams.com.mx | D18: Autoservicio / Grocery | E18: No | F18: HTTP 200 · bloqueo bot (revisar en Chrome/Ghostery) | G18: Red (navegador) + HTML/GTM | H18: 3 | BA18: 1 | BF18: 1 | BG18: 1
A19: 17 | B19: Costco México | C19: costco.com.mx | D19: Autoservicio / Grocery | E19: No | F19: HTTP 200 | G19: Red (navegador) + HTML/GTM | H19: 5 | I19: GTM-PVSS4SK | K19: 1 | AL19: 1 | BD19: 1 | BF19: 1 | BZ19: 1
A20: 18 | B20: Soriana | C20: soriana.com | D20: Autoservicio / Grocery | E20: Sí | F20: HTTP 403 · bloqueo bot (revisar en Chrome/Ghostery) | G20: Red (navegador) + HTML/GTM | H20: 2 | BF20: 1 | CJ20: 1
A21: 19 | B21: Chedraui | C21: chedraui.com.mx | D21: Autoservicio / Grocery | E21: Sí | F21: BLOQUEADO · revisar en Chrome/Ghostery | H21: 0
A22: 20 | B22: La Comer | C22: lacomer.com.mx | D22: Autoservicio / Grocery | E22: No | F22: BLOQUEADO · revisar en Chrome/Ghostery | H22: 0
A23: 21 | B23: HEB México | C23: heb.com.mx | D23: Autoservicio / Grocery | E23: No | F23: HTTP 200 | G23: Red (navegador) + HTML/GTM | H23: 10 | I23: GTM-MDLCJGHZ, GTM-P4HR233H | J23: MMP instalado (atribución app lista) | K23: 1 | L23: 1 | M23: 1 | R23: 1 | S23: 1 | AK23: 1 | AL23: 1 | BD23: 1 | BF23: 1 | BV23: 1
A24: 22 | B24: Rappi | C24: rappi.com.mx | D24: Delivery / QSR | E24: Sí | F24: HTTP 200 | G24: Red (navegador) + HTML/GTM | H24: 12 | I24: GTM-WJZNQMX | J24: MMP instalado (atribución app lista) | K24: 1 | L24: 1 | M24: 1 | R24: 1 | AG24: 1 | AK24: 1 | AL24: 1 | AV24: 1 | BD24: 1 | BF24: 1 | BI24: 1 | BP24: 1
A25: 23 | B25: Uber Eats México | C25: ubereats.com | D25: Delivery / QSR | E25: No | F25: HTTP 200 | G25: Red (navegador) + HTML/GTM | H25: 17 | J25: Retargeting a CPA/CPC (RTB House/Criteo/Smarterclick) · MMP instalado (atribución app lista) · Native/performance | K25: 1 | L25: 1 | M25: 1 | O25: 1 | Q25: 1 | R25: 1 | S25: 1 | T25: 1 | Y25: 1 | AK25: 1 | AO25: 1 | BE25: 1 | BF25: 1 | BG25: 1 | BJ25: 1 | CC25: 1 | CJ25: 1
A26: 24 | B26: DiDi Food México | C26: didiglobal.com | D26: Delivery / QSR | E26: No | F26: HTTP 200 | G26: Red (navegador) + HTML/GTM | H26: 3 | J26: Programa de afiliados activo (ya paga CPA) | L26: 1 | Z26: 1 | BF26: 1
A27: 25 | B27: Jüsto | C27: justo.mx | D27: Autoservicio / Grocery | E27: No | F27: HTTP 200 | G27: Red (navegador) + HTML/GTM | H27: 7 | I27: GTM-M2CF26XG | J27: Stack de data compatible con LSIX | M27: 1 | BB27: 1 | BD27: 1 | BF27: 1 | BH27: 1 | BY27: 1 | CJ27: 1
A28: 26 | B28: Alsea (Domino's / Starbucks / BK / Vips) | C28: alsea.com.mx | D28: Delivery / QSR | E28: Sí | F28: HTTP 200 | G28: Red (navegador) + HTML/GTM | H28: 2 | I28: GTM-W3FHXCVX | BD28: 1 | BF28: 1
A29: 27 | B29: McDonald's México (Arcos Dorados) | C29: mcdonalds.com.mx | D29: Delivery / QSR | E29: No | F29: HTTP 200 | G29: Red (navegador) + HTML/GTM | H29: 8 | I29: GTM-M3L33JX | K29: 1 | L29: 1 | M29: 1 | Q29: 1 | AL29: 1 | BD29: 1 | BF29: 1 | BJ29: 1
A30: 28 | B30: KFC México (Yum!) | C30: kfc.com.mx | D30: Delivery / QSR | E30: No | F30: HTTP 200 | G30: HTML/GTM | H30: 1 | BF30: 1
A31: 29 | B31: Little Caesars México | C31: littlecaesars.com.mx | D31: Delivery / QSR | E31: No | F31: HTTP 200 | G31: Red (navegador) + HTML/GTM | H31: 11 | I31: GTM-TM9J6BJ | J31: Retargeting a CPA/CPC (RTB House/Criteo/Smarterclick) · MMP instalado (atribución app lista) · Native/performance | K31: 1 | L31: 1 | Q31: 1 | S31: 1 | T31: 1 | X31: 1 | Y31: 1 | AJ31: 1 | AO31: 1 | BD31: 1 | BF31: 1
A32: 30 | B32: Farmacias del Ahorro | C32: fahorro.com | D32: Farmacia | E32: Sí | F32: HTTP 200 | G32: Red (navegador) + HTML/GTM | H32: 13 | I32: GTM-P6QK8GFJ | J32: Retargeting a CPA/CPC (RTB House/Criteo/Smarterclick) | K32: 1 | L32: 1 | M32: 1 | P32: 1 | R32: 1 | T32: 1 | U32: 1 | AL32: 1 | BA32: 1 | BD32: 1 | BF32: 1 | BG32: 1 | CG32: 1
A33: 31 | B33: Farmacias Guadalajara | C33: farmaciasguadalajara.com | D33: Farmacia | E33: Sí | F33: BLOQUEADO · revisar en Chrome/Ghostery | H33: 0
A34: 32 | B34: Farmacias Benavides | C34: benavides.com.mx | D34: Farmacia | E34: No | F34: HTTP 200 | G34: Red (navegador) + HTML/GTM | H34: 10 | I34: GTM-NWNRF9Q | J34: Dynamic remarketing Google activo · MMP instalado (atribución app lista) | K34: 1 | L34: 1 | M34: 1 | V34: 1 | AG34: 1 | AL34: 1 | BD34: 1 | BF34: 1 | BJ34: 1 | CG34: 1
A35: 33 | B35: Farmacias San Pablo | C35: farmaciasanpablo.com.mx | D35: Farmacia | E35: No | F35: BLOQUEADO · revisar en Chrome/Ghostery | H35: 0
A36: 34 | B36: Farmacias Similares | C36: farmaciasdesimilares.com | D36: Farmacia | E36: No | F36: BLOQUEADO · revisar en Chrome/Ghostery | H36: 0
A37: 35 | B37: Sephora México | C37: sephora.com.mx | D37: Beauty | E37: Sí | F37: HTTP 403 · bloqueo bot (revisar en Chrome/Ghostery) | G37: Ghostery manual | H37: 9 | J37: Retargeting a CPA/CPC (RTB House/Criteo/Smarterclick) · Dynamic remarketing Google activo | K37: 1 | U37: 1 | V37: 1 | W37: 1 | AL37: 1 | AP37: 1 | AQ37: 1 | AW37: 1 | BD37: 1
A38: 36 | B38: Grisi | C38: grisi.com | D38: Beauty | E38: Sí | F38: HTTP 200 | G38: Red (navegador) + HTML/GTM | H38: 4 | I38: GTM-NLMWRGQP | K38: 1 | AL38: 1 | BD38: 1 | BF38: 1
A39: 37 | B39: Natura &Co (Natura / Avon) | C39: natura.com.mx | D39: Beauty | E39: No | F39: BLOQUEADO · revisar en Chrome/Ghostery | H39: 0
A40: 38 | B40: Mary Kay México | C40: marykay.com.mx | D40: Beauty | E40: No | F40: HTTP 200 | G40: Red (navegador) + HTML/GTM | H40: 7 | I40: GTM-TBN3TQR6 | K40: 1 | AL40: 1 | BD40: 1 | BF40: 1 | BO40: 1 | CF40: 1 | CJ40: 1
A41: 39 | B41: Jafra | C41: jafra.com.mx | D41: Beauty | E41: No | F41: HTTP 200 | G41: Red (navegador) + HTML/GTM | H41: 8 | J41: Programa de afiliados activo (ya paga CPA) | Z41: 1 | BD41: 1 | BF41: 1 | BJ41: 1 | CA41: 1 | CD41: 1 | CE41: 1 | CJ41: 1
A42: 40 | B42: Sally Beauty México | C42: sallybeauty.com.mx | D42: Beauty | E42: No | F42: HTTP 200 | G42: Red (navegador) + HTML/GTM | H42: 9 | I42: GTM-4A0B20B, GTM-PP552LP6 | J42: Dynamic remarketing Google activo | K42: 1 | L42: 1 | M42: 1 | V42: 1 | AL42: 1 | BD42: 1 | BF42: 1 | BJ42: 1 | CE42: 1
A43: 41 | B43: Zara / Inditex México | C43: zara.com/mx | D43: Moda / Calzado | E43: No | F43: BLOQUEADO · revisar en Chrome/Ghostery | H43: 0
A44: 42 | B44: H&M México | C44: hm.com/mx | D44: Moda / Calzado | E44: No | F44: BLOQUEADO · revisar en Chrome/Ghostery | H44: 0
A45: 43 | B45: C&A México | C45: cyamoda.com | D45: Moda / Calzado | E45: No | F45: HTTP 200 | G45: Red (navegador) + HTML/GTM | H45: 19 | I45: GTM-T58RBTG | J45: Dynamic remarketing Google activo · Stack de data compatible con LSIX | K45: 1 | L45: 1 | M45: 1 | N45: 1 | P45: 1 | V45: 1 | AL45: 1 | AO45: 1 | AT45: 1 | AY45: 1 | BB45: 1 | BC45: 1 | BD45: 1 | BF45: 1 | BJ45: 1 | CB45: 1 | CD45: 1 | CF45: 1 | CJ45: 1
A46: 44 | B46: Shasa | C46: shasa.com | D46: Moda / Calzado | E46: No | F46: HTTP 200 | G46: Red (navegador) + HTML/GTM | H46: 12 | I46: GTM-N5FBJ8H | K46: 1 | L46: 1 | M46: 1 | AL46: 1 | BD46: 1 | BF46: 1 | BJ46: 1 | BS46: 1 | BT46: 1 | CB46: 1 | CD46: 1 | CJ46: 1
A47: 45 | B47: Andrea | C47: andrea.com | D47: Moda / Calzado | E47: No | F47: HTTP 200 | G47: Red (navegador) | H47: 11 | I47: GTM-PM44RKR | J47: Retargeting a CPA/CPC (RTB House/Criteo/Smarterclick) · Dynamic remarketing Google activo · Programa de afiliados activo (ya paga CPA) | K47: 1 | L47: 1 | R47: 1 | U47: 1 | V47: 1 | AD47: 1 | AL47: 1 | BD47: 1 | BF47: 1 | BJ47: 1 | CE47: 1
A48: 46 | B48: Price Shoes | C48: priceshoes.com | D48: Moda / Calzado | E48: No | F48: HTTP 200 | G48: Red (navegador) + HTML/GTM | H48: 9 | I48: GTM-PMSWCC6 | J48: Programa de afiliados activo (ya paga CPA) | K48: 1 | L48: 1 | M48: 1 | Z48: 1 | AL48: 1 | BD48: 1 | BF48: 1 | BI48: 1 | BJ48: 1
A49: 47 | B49: Flexi | C49: flexi.com.mx | D49: Moda / Calzado | E49: No | F49: BLOQUEADO · revisar en Chrome/Ghostery | H49: 0
A50: 48 | B50: Cuadra | C50: cuadra.com.mx | D50: Moda / Calzado | E50: No | F50: ERROR: TimeoutError | G50: Red (navegador) + HTML/GTM | H50: 12 | I50: GTM-MD865DGX | J50: Programa de afiliados activo (ya paga CPA) | K50: 1 | L50: 1 | M50: 1 | N50: 1 | AD50: 1 | AL50: 1 | BD50: 1 | BF50: 1 | BS50: 1 | CA50: 1 | CD50: 1 | CJ50: 1
A51: 49 | B51: Nike México | C51: nike.com/mx | D51: Deportes | E51: No | F51: HTTP 200 | G51: HTML/GTM | H51: 5 | J51: Retargeting a CPA/CPC (RTB House/Criteo/Smarterclick) · MMP instalado (atribución app lista) | L51: 1 | U51: 1 | AG51: 1 | BF51: 1 | BG51: 1
A52: 50 | B52: Adidas México | C52: adidas.mx | D52: Deportes | E52: No | F52: HTTP 403 · bloqueo bot (revisar en Chrome/Ghostery) | G52: Red (navegador) + HTML/GTM | H52: 1 | BE52: 1
A53: 51 | B53: Innovasport | C53: innovasport.com | D53: Deportes | E53: No | F53: HTTP 200 | G53: Red (navegador) + HTML/GTM | H53: 23 | I53: GTM-MRFDTGD | J53: Retargeting a CPA/CPC (RTB House/Criteo/Smarterclick) · Dynamic remarketing Google activo · Programa de afiliados activo (ya paga CPA) · MMP instalado (atribución app lista) · Native/performance | K53: 1 | L53: 1 | M53: 1 | P53: 1 | Q53: 1 | R53: 1 | T53: 1 | U53: 1 | V53: 1 | X53: 1 | Z53: 1 | AD53: 1 | AG53: 1 | AL53: 1 | BD53: 1 | BF53: 1 | BI53: 1 | BJ53: 1 | BN53: 1 | BY53: 1 | BZ53: 1 | CH53: 1 | CJ53: 1
A54: 52 | B54: Martí | C54: marti.mx | D54: Deportes | E54: No | F54: HTTP 503 · bloqueo bot (revisar en Chrome/Ghostery) | G54: HTML/GTM | H54: 15 | I54: GTM-K46QC2Z | J54: Retargeting a CPA/CPC (RTB House/Criteo/Smarterclick) · Native/performance | K54: 1 | L54: 1 | M54: 1 | R54: 1 | T54: 1 | U54: 1 | X54: 1 | AL54: 1 | BD54: 1 | BF54: 1 | BJ54: 1 | BK54: 1 | BZ54: 1 | CC54: 1 | CE54: 1
A55: 53 | B55: Dportenis | C55: dportenis.mx | D55: Deportes | E55: No | F55: HTTP 200 | G55: Red (navegador) + HTML/GTM | H55: 7 | I55: GTM-54PXR9B | K55: 1 | L55: 1 | M55: 1 | BD55: 1 | BF55: 1 | BK55: 1 | BO55: 1
A56: 54 | B56: Calzzapato | C56: calzzapato.com | D56: Moda / Calzado | E56: No | F56: ERROR: TimeoutError | G56: Red (navegador) + HTML/GTM | H56: 6 | I56: GTM-5KJJF54 | K56: 1 | AL56: 1 | BD56: 1 | BF56: 1 | BJ56: 1 | CD56: 1
A57: 55 | B57: Decathlon México | C57: decathlon.com.mx | D57: Deportes | E57: No | F57: HTTP 403 · bloqueo bot (revisar en Chrome/Ghostery) | G57: Red (navegador) | H57: 1 | CJ57: 1
A58: 56 | B58: Apple México | C58: apple.com/mx | D58: Electrónica / Tech | E58: No | F58: HTTP 200 | G58: HTML/GTM | H58: 3 | BF58: 1 | BG58: 1 | BK58: 1
A59: 57 | B59: iShop (Grupo Mixup) | C59: ishopmixup.com | D59: Electrónica / Tech | E59: No | F59: BLOQUEADO · revisar en Chrome/Ghostery | H59: 0
A60: 58 | B60: Samsung México | C60: samsung.com/mx | D60: Electrónica / Tech | E60: No | F60: HTTP 200 | G60: Red (navegador) + HTML/GTM | H60: 15 | J60: Retargeting a CPA/CPC (RTB House/Criteo/Smarterclick) · Dynamic remarketing Google activo · Programa de afiliados activo (ya paga CPA) · Native/performance | K60: 1 | T60: 1 | V60: 1 | X60: 1 | Z60: 1 | AL60: 1 | AS60: 1 | AT60: 1 | BA60: 1 | BE60: 1 | BF60: 1 | BG60: 1 | BK60: 1 | BZ60: 1 | CH60: 1
A61: 59 | B61: Xiaomi México | C61: mi.com/mx | D61: Electrónica / Tech | E61: No | F61: HTTP 403 · bloqueo bot (revisar en Chrome/Ghostery) | G61: HTML/GTM | H61: 12 | I61: GTM-5KRKGGMR, GTM-N7BDPG6 | J61: Programa de afiliados activo (ya paga CPA) · Stack de data compatible con LSIX | K61: 1 | L61: 1 | M61: 1 | Q61: 1 | R61: 1 | Z61: 1 | AL61: 1 | BB61: 1 | BD61: 1 | BF61: 1 | BJ61: 1 | BR61: 1
A62: 60 | B62: Steren | C62: steren.com.mx | D62: Electrónica / Tech | E62: No | F62: HTTP 200 | G62: Red (navegador) + HTML/GTM | H62: 13 | I62: GTM-TT936SK | J62: Programa de afiliados activo (ya paga CPA) | K62: 1 | L62: 1 | M62: 1 | N62: 1 | Z62: 1 | AL62: 1 | BD62: 1 | BF62: 1 | BT62: 1 | CC62: 1 | CE62: 1 | CG62: 1 | CJ62: 1
A63: 61 | B63: Cyberpuerta | C63: cyberpuerta.mx | D63: Electrónica / Tech | E63: No | F63: HTTP 200 | G63: Red (navegador) + HTML/GTM | H63: 5 | J63: Dynamic remarketing Google activo | K63: 1 | V63: 1 | AL63: 1 | BD63: 1 | BF63: 1
A64: 62 | B64: RadioShack México | C64: radioshack.com.mx | D64: Electrónica / Tech | E64: No | F64: HTTP 200 | G64: Red (navegador) + HTML/GTM | H64: 12 | I64: GTM-5FBJV7 | J64: Retargeting a CPA/CPC (RTB House/Criteo/Smarterclick) · Programa de afiliados activo (ya paga CPA) | K64: 1 | L64: 1 | M64: 1 | U64: 1 | AD64: 1 | AL64: 1 | AM64: 1 | BD64: 1 | BF64: 1 | BJ64: 1 | BN64: 1 | CJ64: 1
A65: 63 | B65: Home Depot México | C65: homedepot.com.mx | D65: Hogar / Oficina / Variedad | E65: Sí | F65: ERROR: TimeoutError | G65: Red (navegador) + HTML/GTM | H65: 21 | I65: GTM-TSRHVNK | J65: Retargeting a CPA/CPC (RTB House/Criteo/Smarterclick) · Programa de afiliados activo (ya paga CPA) | K65: 1 | L65: 1 | M65: 1 | N65: 1 | Q65: 1 | R65: 1 | T65: 1 | U65: 1 | AC65: 1 | AD65: 1 | AE65: 1 | AL65: 1 | BA65: 1 | BD65: 1 | BF65: 1 | BG65: 1 | BI65: 1 | BK65: 1 | BN65: 1 | BY65: 1 | BZ65: 1
A66: 64 | B66: Sodimac México | C66: sodimac.com.mx | D66: Hogar / Oficina / Variedad | E66: No | F66: HTTP 200 | G66: Red (navegador) + HTML/GTM | H66: 20 | I66: GTM-MCX5LCV | J66: Retargeting a CPA/CPC (RTB House/Criteo/Smarterclick) · Programa de afiliados activo (ya paga CPA) · MMP instalado (atribución app lista) · Stack de data compatible con LSIX | K66: 1 | L66: 1 | M66: 1 | N66: 1 | R66: 1 | T66: 1 | U66: 1 | Z66: 1 | AG66: 1 | AL66: 1 | BB66: 1 | BD66: 1 | BF66: 1 | BG66: 1 | BJ66: 1 | BK66: 1 | BO66: 1 | BW66: 1 | CE66: 1 | CJ66: 1
A67: 65 | B67: IKEA México | C67: ikea.com/mx | D67: Hogar / Oficina / Variedad | E67: No | F67: HTTP 200 | G67: HTML/GTM | H67: 2 | BF67: 1 | BK67: 1
A68: 66 | B68: Gaia Design | C68: gaiadesign.com.mx | D68: Hogar / Oficina / Variedad | E68: No | F68: HTTP 200 | G68: Red (navegador) + HTML/GTM | H68: 7 | K68: 1 | M68: 1 | BF68: 1 | BJ68: 1 | BK68: 1 | BS68: 1 | CD68: 1
A69: 67 | B69: Office Depot México | C69: officedepot.com.mx | D69: Hogar / Oficina / Variedad | E69: No | F69: HTTP 200 | G69: Red (navegador) + HTML/GTM | H69: 21 | I69: GTM-56PS9J8 | J69: Retargeting a CPA/CPC (RTB House/Criteo/Smarterclick) · Dynamic remarketing Google activo · Programa de afiliados activo (ya paga CPA) · Native/performance | K69: 1 | L69: 1 | M69: 1 | Q69: 1 | R69: 1 | U69: 1 | V69: 1 | X69: 1 | Z69: 1 | AD69: 1 | AE69: 1 | AL69: 1 | AM69: 1 | BD69: 1 | BF69: 1 | BJ69: 1 | BN69: 1 | BS69: 1 | CE69: 1 | CH69: 1 | CJ69: 1
A70: 68 | B70: Waldo's | C70: waldos.com.mx | D70: Hogar / Oficina / Variedad | E70: No | F70: BLOQUEADO · revisar en Chrome/Ghostery | H70: 0
A71: 69 | B71: Miniso México | C71: miniso.com.mx | D71: Hogar / Oficina / Variedad | E71: No | F71: BLOQUEADO · revisar en Chrome/Ghostery | H71: 0
A72: 70 | B72: Tiendas Del Sol / Woolworth | C72: delsol.com.mx | D72: Departamental | E72: No | F72: BLOQUEADO · revisar en Chrome/Ghostery | H72: 0
A73: 71 | B73: Volaris | C73: volaris.com | D73: Travel / Movilidad | E73: Sí | F73: HTTP 200 | G73: Red (navegador) + HTML/GTM | H73: 12 | I73: GTM-S4SJ | J73: Retargeting a CPA/CPC (RTB House/Criteo/Smarterclick) · Dynamic remarketing Google activo | K73: 1 | L73: 1 | R73: 1 | U73: 1 | V73: 1 | AL73: 1 | AN73: 1 | AO73: 1 | AR73: 1 | BD73: 1 | BE73: 1 | BF73: 1
A74: 72 | B74: Viva | C74: vivaaerobus.com | D74: Travel / Movilidad | E74: Sí | F74: BLOQUEADO · revisar en Chrome/Ghostery | G74: HTML/GTM | H74: 1 | BF74: 1
A75: 73 | B75: Aeroméxico | C75: aeromexico.com | D75: Travel / Movilidad | E75: Sí | F75: BLOQUEADO · revisar en Chrome/Ghostery | H75: 0
A76: 74 | B76: Despegar México | C76: despegar.com.mx | D76: Travel / Movilidad | E76: No | F76: BLOQUEADO · revisar en Chrome/Ghostery | H76: 0
A77: 75 | B77: PriceTravel | C77: pricetravel.com | D77: Travel / Movilidad | E77: No | F77: HTTP 200 | G77: Red (navegador) + HTML/GTM | H77: 11 | I77: GTM-K79L3DNV | J77: Programa de afiliados activo (ya paga CPA) | K77: 1 | L77: 1 | M77: 1 | R77: 1 | AD77: 1 | AL77: 1 | BD77: 1 | BF77: 1 | BI77: 1 | BR77: 1 | BY77: 1
A78: 76 | B78: Best Day | C78: bestday.com.mx | D78: Travel / Movilidad | E78: No | F78: BLOQUEADO · revisar en Chrome/Ghostery | H78: 0
A79: 77 | B79: Grupo Posadas (Fiesta Americana) | C79: posadas.com | D79: Travel / Movilidad | E79: No | F79: HTTP 200 | G79: Red (navegador) + HTML/GTM | H79: 20 | I79: GTM-K9BF787, GTM-KDXDKJZ7, GTM-KVQFZZZH, GTM-M44H2TWH, GTM-MNHSB9X6, GTM-P4G3NR6K, GTM-WLNRQ7XN | J79: Retargeting a CPA/CPC (RTB House/Criteo/Smarterclick) · Dynamic remarketing Google activo · Programa de afiliados activo (ya paga CPA) · Native/performance | K79: 1 | L79: 1 | M79: 1 | N79: 1 | P79: 1 | R79: 1 | S79: 1 | T79: 1 | U79: 1 | V79: 1 | X79: 1 | AD79: 1 | AE79: 1 | AL79: 1 | BD79: 1 | BF79: 1 | BI79: 1 | BJ79: 1 | BK79: 1 | BN79: 1
A80: 78 | B80: Hoteles City Express | C80: cityexpress.com | D80: Travel / Movilidad | E80: No | F80: HTTP 200 | G80: Red (navegador) + HTML/GTM | H80: 12 | J80: Programa de afiliados activo (ya paga CPA) | K80: 1 | R80: 1 | AF80: 1 | AL80: 1 | AN80: 1 | AO80: 1 | AR80: 1 | AT80: 1 | BA80: 1 | BF80: 1 | BG80: 1 | BL80: 1
A81: 79 | B81: ADO | C81: ado.com.mx | D81: Travel / Movilidad | E81: No | F81: HTTP 200 | G81: Red (navegador) + HTML/GTM | H81: 9 | I81: GTM-PCS8N3B | J81: Dynamic remarketing Google activo | K81: 1 | L81: 1 | V81: 1 | AL81: 1 | BD81: 1 | BF81: 1 | BT81: 1 | CB81: 1 | CE81: 1
A82: 80 | B82: Cinépolis | C82: cinepolis.com | D82: Entretenimiento / Ticketing | E82: Sí | F82: BLOQUEADO · revisar en Chrome/Ghostery | H82: 0
A83: 81 | B83: Cinemex | C83: cinemex.com | D83: Entretenimiento / Ticketing | E83: No | F83: HTTP 200 | G83: Red (navegador) + HTML/GTM | H83: 18 | I83: GTM-T9NZ56T | J83: Dynamic remarketing Google activo · Programa de afiliados activo (ya paga CPA) | K83: 1 | L83: 1 | M83: 1 | N83: 1 | Q83: 1 | R83: 1 | V83: 1 | Z83: 1 | AD83: 1 | AL83: 1 | BD83: 1 | BF83: 1 | BI83: 1 | BJ83: 1 | BK83: 1 | BM83: 1 | BO83: 1 | CE83: 1
A84: 82 | B84: Ticketmaster México (OCESA) | C84: ticketmaster.com.mx | D84: Entretenimiento / Ticketing | E84: No | F84: HTTP 403 · bloqueo bot (revisar en Chrome/Ghostery) | G84: Red (navegador) | H84: 1 | I84: GTM-5MZG6PB6, GTM-5TNTJSSJ, GTM-K4QMLG, GTM-M6BK9TM5, GTM-N93JW5V, GTM-NMC3FK4, GTM-NMSNF2L, GTM-PLDTF3KT, GTM-PSVWZZC, GTM-TB7ZTT2, GTM-TT3LTJWW, GTM-WW62QPR | BD84: 1
A85: 83 | B85: Boletia | C85: boletia.com | D85: Entretenimiento / Ticketing | E85: No | F85: BLOQUEADO · revisar en Chrome/Ghostery | H85: 0
A86: 84 | B86: AutoZone México | C86: autozone.com.mx | D86: Auto | E86: No | F86: HTTP 403 · bloqueo bot (revisar en Chrome/Ghostery) | G86: Red (navegador) + HTML/GTM | H86: 6 | J86: Dynamic remarketing Google activo | K86: 1 | L86: 1 | V86: 1 | BA86: 1 | BE86: 1 | BG86: 1
A87: 85 | B87: Kavak | C87: kavak.com/mx | D87: Auto | E87: No | F87: BLOQUEADO · revisar en Chrome/Ghostery | H87: 0
A88: 86 | B88: Italika | C88: italika.mx | D88: Auto | E88: No | F88: HTTP 200 | G88: Red (navegador) + HTML/GTM | H88: 15 | I88: GTM-NBVGGJRV, GTM-NH38TGW | J88: Retargeting a CPA/CPC (RTB House/Criteo/Smarterclick) | K88: 1 | L88: 1 | M88: 1 | U88: 1 | AL88: 1 | BA88: 1 | BD88: 1 | BF88: 1 | BG88: 1 | BI88: 1 | BJ88: 1 | BK88: 1 | BN88: 1 | CH88: 1 | CJ88: 1
A89: 87 | B89: Petco México | C89: petco.com.mx | D89: Nicho (mascotas, libros, juguetes, óptica, regalos) | E89: No | F89: HTTP 200 | G89: Red (navegador) + HTML/GTM | H89: 12 | I89: GTM-NRNT24 | J89: Retargeting a CPA/CPC (RTB House/Criteo/Smarterclick) | K89: 1 | L89: 1 | M89: 1 | S89: 1 | U89: 1 | AL89: 1 | AM89: 1 | BD89: 1 | BF89: 1 | BK89: 1 | BN89: 1 | CJ89: 1
A90: 88 | B90: +Kota | C90: maskota.com.mx | D90: Nicho (mascotas, libros, juguetes, óptica, regalos) | E90: No | F90: HTTP 200 | G90: Red (navegador) + HTML/GTM | H90: 8 | J90: Dynamic remarketing Google activo | K90: 1 | L90: 1 | M90: 1 | V90: 1 | BF90: 1 | BK90: 1 | CD90: 1 | CJ90: 1
A91: 89 | B91: Librerías Gandhi | C91: gandhi.com.mx | D91: Nicho (mascotas, libros, juguetes, óptica, regalos) | E91: No | F91: HTTP 200 | G91: Red (navegador) + HTML/GTM | H91: 15 | I91: GTM-TM6PXGTV | J91: Dynamic remarketing Google activo · Programa de afiliados activo (ya paga CPA) | K91: 1 | L91: 1 | M91: 1 | V91: 1 | Z91: 1 | AE91: 1 | AL91: 1 | BD91: 1 | BF91: 1 | BJ91: 1 | BK91: 1 | BU91: 1 | BZ91: 1 | CC91: 1 | CE91: 1
A92: 90 | B92: Porrúa | C92: porrua.mx | D92: Nicho (mascotas, libros, juguetes, óptica, regalos) | E92: No | F92: HTTP 200 | G92: Red (navegador) + HTML/GTM | H92: 3 | L92: 1 | BF92: 1 | CG92: 1
A93: 91 | B93: Juguetrón | C93: juguetron.mx | D93: Nicho (mascotas, libros, juguetes, óptica, regalos) | E93: No | F93: HTTP 200 | G93: Red (navegador) + HTML/GTM | H93: 18 | I93: GTM-57SQR5N3 | J93: Dynamic remarketing Google activo · Programa de afiliados activo (ya paga CPA) | K93: 1 | L93: 1 | M93: 1 | N93: 1 | V93: 1 | Z93: 1 | AL93: 1 | BD93: 1 | BF93: 1 | BI93: 1 | BJ93: 1 | BO93: 1 | BU93: 1 | BY93: 1 | CB93: 1 | CC93: 1 | CD93: 1 | CE93: 1
A94: 92 | B94: Julio Cepeda Jugueterías | C94: juliocepeda.com | D94: Nicho (mascotas, libros, juguetes, óptica, regalos) | E94: No | F94: HTTP 200 | G94: Red (navegador) + HTML/GTM | H94: 7 | I94: GTM-5X5Q6F | K94: 1 | L94: 1 | AL94: 1 | BD94: 1 | BF94: 1 | BI94: 1 | CD94: 1
A95: 93 | B95: Ópticas Devlyn | C95: devlyn.com.mx | D95: Nicho (mascotas, libros, juguetes, óptica, regalos) | E95: No | F95: HTTP 200 | G95: Red (navegador) | H95: 9 | I95: GTM-KV7VF5N | K95: 1 | L95: 1 | M95: 1 | R95: 1 | BD95: 1 | BF95: 1 | BI95: 1 | BJ95: 1 | CE95: 1
A96: 94 | B96: Enviaflores | C96: enviaflores.com | D96: Nicho (mascotas, libros, juguetes, óptica, regalos) | E96: No | F96: HTTP 200 | G96: Red (navegador) + HTML/GTM | H96: 14 | I96: GTM-NZPDMCDQ | J96: Dynamic remarketing Google activo · Programa de afiliados activo (ya paga CPA) · MMP instalado (atribución app lista) | K96: 1 | L96: 1 | M96: 1 | R96: 1 | V96: 1 | Z96: 1 | AE96: 1 | AK96: 1 | AL96: 1 | BD96: 1 | BF96: 1 | BI96: 1 | BQ96: 1 | CE96: 1
A97: 95 | B97: Mercado Pago | C97: mercadopago.com.mx | D97: Fintech / BNPL / Wallet | E97: Sí | F97: HTTP 200 | G97: Red (navegador) + HTML/GTM | H97: 20 | I97: GTM-NRDZZ97 | J97: Retargeting a CPA/CPC (RTB House/Criteo/Smarterclick) · Programa de afiliados activo (ya paga CPA) · MMP instalado (atribución app lista) · Native/performance | K97: 1 | L97: 1 | M97: 1 | N97: 1 | P97: 1 | Q97: 1 | R97: 1 | S97: 1 | T97: 1 | U97: 1 | Y97: 1 | Z97: 1 | AH97: 1 | AL97: 1 | BD97: 1 | BF97: 1 | BI97: 1 | BK97: 1 | BT97: 1 | CD97: 1
A98: 96 | B98: Kueski Pay | C98: kueskipay.com | D98: Fintech / BNPL / Wallet | E98: Sí | F98: HTTP 200 | G98: Red (navegador) + HTML/GTM | H98: 13 | I98: GTM-TMLW9N2, GTM-W2DRGQD | J98: Retargeting a CPA/CPC (RTB House/Criteo/Smarterclick) · MMP instalado (atribución app lista) | K98: 1 | L98: 1 | M98: 1 | R98: 1 | S98: 1 | T98: 1 | AK98: 1 | AL98: 1 | BD98: 1 | BF98: 1 | BI98: 1 | BP98: 1 | BT98: 1
A99: 97 | B99: Aplazo | C99: aplazo.mx | D99: Fintech / BNPL / Wallet | E99: No | F99: HTTP 200 | G99: Red (navegador) + HTML/GTM | H99: 15 | I99: GTM-TXFSFDT | J99: Dynamic remarketing Google activo · Programa de afiliados activo (ya paga CPA) · MMP instalado (atribución app lista) | K99: 1 | L99: 1 | M99: 1 | N99: 1 | P99: 1 | Q99: 1 | V99: 1 | AE99: 1 | AH99: 1 | AL99: 1 | BD99: 1 | BF99: 1 | BI99: 1 | BT99: 1 | BY99: 1
A100: 98 | B100: Telcel (Tienda en línea / Mi Telcel) | C100: telcel.com | D100: Telco | E100: Sí | F100: HTTP 200 | G100: Red (navegador) | H100: 21 | I100: GTM-M8HM3D | J100: Dynamic remarketing Google activo · Stack de data compatible con LSIX | K100: 1 | L100: 1 | M100: 1 | Q100: 1 | R100: 1 | V100: 1 | AL100: 1 | AN100: 1 | AO100: 1 | AR100: 1 | AX100: 1 | AY100: 1 | BA100: 1 | BB100: 1 | BD100: 1 | BF100: 1 | BG100: 1 | BI100: 1 | BJ100: 1 | BN100: 1 | BO100: 1
...

Sheet Detalle_Largo
A1: Empresa | B1: Dominio | C1: Categoría empresa | D1: En CRM | E1: Vendor / pixel | F1: Categoría vendor | G1: Método detección
A2: Mercado Libre | B2: mercadolibre.com.mx | C2: Marketplace | D2: Sí | E2: GA4 | F2: Analytics | G2: HTML/GTM
A3: Mercado Libre | B3: mercadolibre.com.mx | C3: Marketplace | D3: Sí | E3: Hotjar | F3: UX | G3: Red+HTML/GTM
A4: Mercado Libre | B4: mercadolibre.com.mx | C4: Marketplace | D4: Sí | E4: Contentsquare | F4: UX | G4: HTML/GTM
A5: Amazon México | B5: amazon.com.mx | C5: Marketplace | D5: Sí | E5: Contentsquare | F5: UX | G5: HTML/GTM
A6: Temu | B6: temu.com | C6: Marketplace | D6: No | E6: Google Ads / gtag | F6: Paid media | G6: HTML/GTM
A7: Temu | B7: temu.com | C7: Marketplace | D7: No | E7: Taboola | F7: Native | G7: HTML/GTM
A8: Temu | B8: temu.com | C8: Marketplace | D8: No | E8: GA4 | F8: Analytics | G8: HTML/GTM
A9: Shein | B9: shein.com.mx | C9: Marketplace | D9: No | E9: Google Ads / gtag | F9: Paid media | G9: HTML/GTM
A10: Shein | B10: shein.com.mx | C10: Marketplace | D10: No | E10: Awin | F10: Afiliados | G10: HTML/GTM
A11: Shein | B11: shein.com.mx | C11: Marketplace | D11: No | E11: Admitad | F11: Afiliados | G11: HTML/GTM
A12: Shein | B12: shein.com.mx | C12: Marketplace | D12: No | E12: GA4 | F12: Analytics | G12: HTML/GTM
... A765: Spin by OXXO (Femsa) | B765: spinbyoxxo.com.mx | C765: Fintech / BNPL / Wallet | D765: Sí | E765: Contentsquare | F765: UX | G765: HTML/GTM

Sheet Pendientes_Chrome_Ghostery
A1: Sitios que bloquearon el scan desde datacenter — revisar desde tu Chrome (IP residencial) con Ghostery o el snippet de consola
A2: # | B2: Empresa | C2: Dominio | D2: Categoría | E2: En CRM | F2: Estatus | G2: Hallazgo Ghostery (llenar) | H2: Fecha revisión
A3: 1 | B3: AliExpress | C3: aliexpress.com | D3: Marketplace | E3: No | F3: BLOQUEADO · revisar en Chrome/Ghostery
A4: 2 | B4: Sears México (Grupo Carso) | C4: sears.com.mx | D4: Departamental | E4: No | F4: BLOQUEADO · revisar en Chrome/Ghostery
A5: 3 | B5: Sanborns | C5: sanborns.com.mx | D5: Departamental | E5: No | F5: BLOQUEADO · revisar en Chrome/Ghostery
A6: 4 | B6: Walmart de México | C6: walmart.com.mx | D6: Autoservicio / Grocery | E6: Sí | F6: BLOQUEADO · revisar en Chrome/Ghostery
A7: 5 | B7: Chedraui | C7: chedraui.com.mx | D7: Autoservicio / Grocery | E7: Sí | F7: BLOQUEADO · revisar en Chrome/Ghostery
A8: 6 | B8: La Comer | C8: lacomer.com.mx | D8: Autoservicio / Grocery | E8: No | F8: BLOQUEADO · revisar en Chrome/Ghostery
A9: 7 | B9: Farmacias Guadalajara | C9: farmaciasguadalajara.com | D9: Farmacia | E9: Sí | F9: BLOQUEADO · revisar en Chrome/Ghostery
A10: 8 | B10: Farmacias San Pablo | C10: farmaciasanpablo.com.mx | D10: Farmacia | E10: No | F10: BLOQUEADO · revisar en Chrome/Ghostery
A11: 9 | B11: Farmacias Similares | C11: farmaciasdesimilares.com | D11: Farmacia | E11: No | F11: BLOQUEADO · revisar en Chrome/Ghostery
A12: 10 | B12: Natura &Co (Natura / Avon) | C12: natura.com.mx | D12: Beauty | E12: No | F12: BLOQUEADO · revisar en Chrome/Ghostery
A13: 11 | B13: Zara / Inditex México | C13: zara.com/mx | D13: Moda / Calzado | E13: No | F13: BLOQUEADO · revisar en Chrome/Ghostery
A14: 12 | B14: H&M México | C14: hm.com/mx | D14: Moda / Calzado | E14: No | F14: BLOQUEADO · revisar en Chrome/Ghostery
... A26: 24 | B26: Kavak | C26: kavak.com/mx | D26: Auto | E26: No | F26: BLOQUEADO · revisar en Chrome/Ghostery
A28: PROTOCOLO (3 min por sitio)
A29: 1. Abre el sitio en Chrome con Ghostery activo en modo 'Nunca bloquear' (solo observar), navega home → categoría → producto → carrito (sin comprar).
A30: 2. Abre el panel de Ghostery → pestaña 'Trackers detectados' → agrupa por categoría Advertising. Anota: RTB House, Criteo, Taboola, Outbrain, Teads, Seedtag, Adform, Xandr, TTD, AppsFlyer/Adjust/Branch, Awin/Impact/CJ/Rakuten/Admitad/Soicos.
A31: 3. Alternativa sin Ghostery — pega en DevTools > Console (F12) el snippet de abajo: lista todos los hosts de terceros cargados en la página actual.
A32: 4. Repite el snippet en la página de producto y en carrito: ahí disparan los pixeles de retargeting dinámico (RTB House/Criteo) que la home no siempre carga.
A33: 5. Pega los hallazgos en la columna 'Hallazgo Ghostery' de esta hoja y marca la fecha.
A35: SNIPPET DEVTOOLS (copia y pega en Console):
A36: (()=>{const h=new Set();performance.getEntriesByType('resource').forEach(e=>{try{h.add(new URL(e.name).hostname)}catch(_){}});const first=location.hostname.split('.').slice(-2).join('.');const out=[...h].filter(x=>!x.endsWith(first)).sort();copy(out.join('\n'));console.log(out.length+' hosts de terceros copiados al portapapeles:\n'+out.join('\n'));})();
A38: PROMPT PARA CLAUDE IN CHROME (ejecuta la lista bloqueada de arriba con tu sesión):
A39: Para cada dominio de la lista que te doy: abre la home, espera 8 segundos, haz scroll al final, entra a una página de producto cualquiera y agrégalo al carrito (no pagues). En cada una de las 3 páginas ejecuta en consola el snippet que te pego y guarda la salida. Al final entrégame una tabla: Dominio | Pixeles de paid media (Meta, Google Ads, TikTok, Pinterest, Snap, Bing) | Retargeting/CPA (RTB House, Criteo) | Native (Taboola, Outbrain) | Afiliados (Awin, Impact, CJ, Rakuten, Admitad, Soicos) | MMP (AppsFlyer, Adjust, Branch, Singular) | DMP/Identity (Retargetly, Lotame, LiveRamp, ID5) | Otros relevantes. No inventes: si un host no aparece en la salida de consola, no lo listes. Lista de dominios: [pegar columna C de esta hoja].

Sheet Benchmarks_CPA
A1: Benchmarks de CPA / CPI por categoría — fuentes públicas de terceros (NO son datos de LSIX)
A2: Uso: referencia para conversación de unit economics. El CPA real de cada anunciante sale de la sesión de unit economics (regla del playbook: nunca comprometer CPA sin ese dato). Cifras en USD.
A4: SUPUESTO (editable)
A5: CPM Meta México (USD) | B5: 3.92 | C5: Fuelads, Benchmarks LatAm Q2 2026 — https://fuelads.tech/benchmarks-latam-2026
A6: CPM Meta EE.UU. (USD) | B6: 16 | C6: Idem
A7: Factor de ajuste MX/US | B7: =B5/B6 -> 0.245
A8: Nota: el factor asume que el CPA escala con el CPM a igual tasa de conversión. Es una aproximación de Fuelads replicada aquí, no un benchmark medido en México. Úsalo como techo de conversación, no como precio.
A10: Categoría (Top100) | B10: Benchmark web más cercano | C10: CPA Meta mediana US (USD) | D10: CPA MX estimado (USD) = US × factor | E10: CPA Google Ads mediana US (USD) | F10: CPI app LatAm (USD, rango) | G10: Tipo de conversión CPA sugerida para LSIX | H10: Fuentes | I10: Confianza
A11: Marketplace | B11: E-commerce general | C11: 29.99 | D11: =IF(ISNUMBER(C11),C11*$B$7,"[PENDIENTE] sin benchmark de categoría") -> 7.34755 | E11: 23.74 | F11: 0.50–2.00 (shopping LatAm; Statista vía BoA: 1.42) | G11: Venta en app (% revenue o CPA fijo) | H11: Ryze AI, Meta Ads Cost Benchmarks by Industry 2026 (abr-2026) — https://www.get-ryze.ai/blog/cost-per-acquisition-benchmarks-2026; Business of Apps, App User Acquisition Costs 2025 (citando Sensor Tower, Adjust, Liftoff, AdAction) — https://www.businessofapps.com/marketplace/user-acquisition/research/user-acquisition-costs/ | I11: Media
A12: Departamental | B12: E-commerce general / Apparel | C12: 29.99 | D12: =IF(ISNUMBER(C12),C12*$B$7,"[PENDIENTE] sin benchmark de categoría") -> 7.34755 | E12: 23.74 | F12: 0.50–2.00 | G12: Venta en app; 1ª compra vs recurrente | H12: Ryze AI, Meta Ads Cost Benchmarks by Industry 2026 (abr-2026) — https://www.get-ryze.ai/blog/cost-per-acquisition-benchmarks-2026; Business of Apps, App User Acquisition Costs 2025 (citando Sensor Tower, Adjust, Liftoff, AdAction) — https://www.businessofapps.com/marketplace/user-acquisition/research/user-acquisition-costs/ | I12: Media
A13: Autoservicio / Grocery | B13: E-commerce general (sin benchmark grocery público) | C13: 29.99 | D13: =IF(ISNUMBER(C13),C13*$B$7,"[PENDIENTE] sin benchmark de categoría") -> 7.34755 | E13: 23.74 | F13: 0.50–2.00 | G13: Pedido en app (ticket bajo → CPA bajo, volumen) | H13: Ryze AI, Meta Ads Cost Benchmarks by Industry 2026 (abr-2026) — https://www.get-ryze.ai/blog/cost-per-acquisition-benchmarks-2026; Business of Apps, App User Acquisition Costs 2025 (citando Sensor Tower, Adjust, Liftoff, AdAction) — https://www.businessofapps.com/marketplace/user-acquisition/research/user-acquisition-costs/ | I13: Baja
A14: Delivery / QSR | B14: Food & Beverage (CPC más bajo 0.52; CPA sin dato público categoría) | C14: [PENDIENTE] | D14: =IF(ISNUMBER(C14),C14*$B$7,"[PENDIENTE] sin benchmark de categoría") -> [PENDIENTE] sin benchmark de categoría | E14: 23.74 | F14: 0.50–2.00 | G14: Primer pedido en app / pedido reactivado | H14: Ryze AI, Meta Ads Cost Benchmarks by Industry 2026 (abr-2026) — https://www.get-ryze.ai/blog/cost-per-acquisition-benchmarks-2026 (CPC); Business of Apps, App User Acquisition Costs 2025 (citando Sensor Tower, Adjust, Liftoff, AdAction) — https://www.businessofapps.com/marketplace/user-acquisition/research/user-acquisition-costs/ | I14: Baja
A15: Farmacia | B15: Health / e-commerce general | C15: 29.99 | D15: =IF(ISNUMBER(C15),C15*$B$7,"[PENDIENTE] sin benchmark de categoría") -> 7.34755 | E15: 23.74 | F15: 0.50–2.00 | G15: Venta en app; recurrencia (crónicos) | H15: Ryze AI, Meta Ads Cost Benchmarks by Industry 2026 (abr-2026) — https://www.get-ryze.ai/blog/cost-per-acquisition-benchmarks-2026; Business of Apps, App User Acquisition Costs 2025 (citando Sensor Tower, Adjust, Liftoff, AdAction) — https://www.businessofapps.com/marketplace/user-acquisition/research/user-acquisition-costs/ | I15: Baja
A16: Beauty | B16: Beauty & Cosmetics (CPL más bajo de la región según Fuelads) | C16: 29.99 | D16: =IF(ISNUMBER(C16),C16*$B$7,"[PENDIENTE] sin benchmark de categoría") -> 7.34755 | E16: 23.74 | F16: 0.50–2.00 | G16: Venta en app / 1ª compra | H16: Ryze AI, Meta Ads Cost Benchmarks by Industry 2026 (abr-2026) — https://www.get-ryze.ai/blog/cost-per-acquisition-benchmarks-2026; Fuelads Q2 2026 | I16: Media
A17: Moda / Calzado | B17: Apparel & Fashion (CPC más bajo: 0.45) | C17: 29.99 | D17: =IF(ISNUMBER(C17),C17*$B$7,"[PENDIENTE] sin benchmark de categoría") -> 7.34755 | E17: 23.74 | F17: 0.50–2.00 | G17: Venta en app; devolución como condición de validez | H17: Ryze AI, Meta Ads Cost Benchmarks by Industry 2026 (abr-2026) — https://www.get-ryze.ai/blog/cost-per-acquisition-benchmarks-2026; Business of Apps, App User Acquisition Costs 2025 (citando Sensor Tower, Adjust, Liftoff, AdAction) — https://www.businessofapps.com/marketplace/user-acquisition/research/user-acquisition-costs/ | I17: Media
A18: Deportes | B18: Apparel / Sporting goods | C18: 29.99 | D18: =IF(ISNUMBER(C18),C18*$B$7,"[PENDIENTE] sin benchmark de categoría") -> 7.34755 | E18: 23.74 | F18: 0.50–2.00 | G18: Venta en app; app install + 1ª compra (Innovasport) | H18: Ryze AI, Meta Ads Cost Benchmarks by Industry 2026 (abr-2026) — https://www.get-ryze.ai/blog/cost-per-acquisition-benchmarks-2026 | I18: Baja
A19: Electrónica / Tech | B19: Electronics (categoría más cara en Meta) | C19: 51.86 | D19: =IF(ISNUMBER(C19),C19*$B$7,"[PENDIENTE] sin benchmark de categoría") -> 12.7057 | E19: 23.74 | F19: 0.50–2.00 | G19: Venta en app (ticket alto → % revenue) | H19: Triple Whale, Facebook Ad Benchmarks (ago-2025→jul-2026, DTC/e-commerce) — https://www.triplewhale.com/blog/facebook-ads-benchmarks | I19: Media
A20: Hogar / Oficina / Variedad | B20: Home & Garden / e-commerce general | C20: 29.99 | D20: =IF(ISNUMBER(C20),C20*$B$7,"[PENDIENTE] sin benchmark de categoría") -> 7.34755 | E20: 23.74 | F20: 0.50–2.00 | G20: Venta en app; ticket alto → % revenue | H20: Ryze AI, Meta Ads Cost Benchmarks by Industry 2026 (abr-2026) — https://www.get-ryze.ai/blog/cost-per-acquisition-benchmarks-2026 | I20: Baja
A21: Travel / Movilidad | B21: Travel (sin CPA público por categoría; Triple Whale: Travel Accessories entre las más caras) | C21: [PENDIENTE] | D21: =IF(ISNUMBER(C21),C21*$B$7,"[PENDIENTE] sin benchmark de categoría") -> [PENDIENTE] sin benchmark de categoría | E21: 23.74 | F21: 0.50–2.00 | G21: Reserva/boleto emitido en app | H21: Triple Whale, Facebook Ad Benchmarks (ago-2025→jul-2026, DTC/e-commerce) — https://www.triplewhale.com/blog/facebook-ads-benchmarks; Business of Apps, App User Acquisition Costs 2025 (citando Sensor Tower, Adjust, Liftoff, AdAction) — https://www.businessofapps.com/marketplace/user-acquisition/research/user-acquisition-costs/ | I21: Baja
A22: Entretenimiento / Ticketing | B22: Entertainment (sin dato público) | C22: [PENDIENTE] | D22: =IF(ISNUMBER(C22),C22*$B$7,"[PENDIENTE] sin benchmark de categoría") -> [PENDIENTE] sin benchmark de categoría | E22: 23.74 | F22: 0.50–2.00 | G22: Boleto comprado en app | H22: Business of Apps, App User Acquisition Costs 2025 (citando Sensor Tower, Adjust, Liftoff, AdAction) — https://www.businessofapps.com/marketplace/user-acquisition/research/user-acquisition-costs/ | I22: Baja
A23: Auto | B23: Automotive (lead-based: CPL, no CPA) | C23: [PENDIENTE] | D23: =IF(ISNUMBER(C23),C23*$B$7,"[PENDIENTE] sin benchmark de categoría") -> [PENDIENTE] sin benchmark de categoría | E23: 23.74 | F23: n/a | G23: Lead calificado (CPL) / cita | H23: Ryze AI, Meta Ads Cost Benchmarks by Industry 2026 (abr-2026) — https://www.get-ryze.ai/blog/cost-per-acquisition-benchmarks-2026 | I23: Baja
A24: Nicho (mascotas, libros, juguetes, óptica, regalos) | B24: Books & Music 30.69 / Toys & Collectibles / Pets | C24: 30.69 | D24: =IF(ISNUMBER(C24),C24*$B$7,"[PENDIENTE] sin benchmark de categoría") -> 7.51905 | E24: 23.74 | F24: 0.50–2.00 | G24: Venta en app; suscripción (mascotas) | H24: Triple Whale, Facebook Ad Benchmarks (ago-2025→jul-2026, DTC/e-commerce) — https://www.triplewhale.com/blog/facebook-ads-benchmarks | I24: Media
A25: Fintech / BNPL / Wallet | B25: Finance (CPI más alto: 2.50–6.00 global; BoA 8.23) | C25: [PENDIENTE] | D25: =IF(ISNUMBER(C25),C25*$B$7,"[PENDIENTE] sin benchmark de categoría") -> [PENDIENTE] sin benchmark de categoría | E25: 23.74 | F25: 2.50–6.00 (global, Adjust/Juniper 2024); LatAm menor — sin dato público MX | G25: Alta/KYC completada, 1ª transacción, crédito desembolsado (CPA por evento, no por install) | H25: Business of Apps, App User Acquisition Costs 2025 (citando Sensor Tower, Adjust, Liftoff, AdAction) — https://www.businessofapps.com/marketplace/user-acquisition/research/user-acquisition-costs/; Insert Affiliate, Mobile App UA Cost Benchmarks (may-2026) — https://insertaffiliate.com/blog/mobile-app-user-acquisition-cost-benchmarks/ | I25: Media
A26: Telco | B26: Telecom (sin CPA público) | C26: [PENDIENTE] | D26: =IF(ISNUMBER(C26),C26*$B$7,"[PENDIENTE] sin benchmark de categoría") -> [PENDIENTE] sin benchmark de categoría | E26: 23.74 | F26: 0.50–2.00 | G26: Alta de línea / portabilidad / recarga en app | H26: Business of Apps, App User Acquisition Costs 2025 (citando Sensor Tower, Adjust, Liftoff, AdAction) — https://www.businessofapps.com/marketplace/user-acquisition/research/user-acquisition-costs/ | I26: Baja
A28: Referencias transversales: CPA mediana Meta todas las industrias US 2026 = $38.19 (Ryze); Triple Whale ago-25→jul-26 = $38.99, ROAS mediana 1.88, CVR 1.53%; CPA Google Ads mediana US 2026 = $23.74 (Ryze); Q4 cuesta 30–40% más que Q1 (Fuelads).
A29: Lo que NO existe públicamente: CPA por anunciante en México. Ese dato solo sale de (a) la sesión de unit economics, (b) el margen/LTV que comparta el cliente, (c) la pregunta de discovery '¿ya compran a CPA con afiliados/redes y a qué precio?' (playbook slide 6).
A30: Los sitios con Awin/Impact/CJ/Admitad/Soicos en la Matriz_Pixeles ya pagan CPA a afiliados: en discovery pide el payout de su programa — es el benchmark real del anunciante y el techo de tu negociación.
A31: Los sitios con RTB House o Criteo ya compran retargeting a CPC/CPA con garantía: el pitch de LSIX compite directamente en ese presupuesto, no en el fee del holding.
